[
    {
        "text": "U xương là tên gọi tình trạng xương xuất hiện khối u do sự phát triển bất thường của tế bào xương.",
        "head": "U xương",
        "head_type": "disease",
        "relation": "isSymptomOf",
        "tail": "Sự phát triển bất thường của tế bào xương",
        "tail_type": "cause"
    },
    {
        "text": "Khối u ở xương có thể lành tính hoặc ác tính, tùy thuộc vào nguyên nhân mà từng người bệnh gặp phải.",
        "head": "Khối u ở xương",
        "head_type": "disease",
        "relation": "causedBy",
        "tail": "Nguyên nhân",
        "tail_type": "cause"
    },
    {
        "text": "Tuy nhiên, tất cả đều là tình trạng đáng báo động vì khối u phát triển sẽ ảnh hưởng đến các mô khỏe mạnh bên trong xương.",
        "head": "Khối u phát triển",
        "head_type": "disease",
        "relation": "affects",
        "tail": "Các mô khỏe mạnh bên trong xương",
        "tail_type": "organ"
    },
    {
        "text": "Và từ đó gây ra những cản trở bất tiện về vận động của người bệnh.",
        "head": "Khối u phát triển",
        "head_type": "disease",
        "relation": "affects",
        "tail": "Vận động",
        "tail_type": "symptom"
    },
    {
        "text": "Khi có các dấu hiệu nghi ngờ u xương, người bệnh cần nhanh chóng đến gặp bác sĩ chuyên môn để được chẩn đoán và điều trị ngay để giảm được các rủi ro bệnh có thể mắc phải.",
        "head": "U xương",
        "head_type": "disease",
        "relation": "diagnosedBy",
        "tail": "Bác sĩ chuyên môn",
        "tail_type": "treatment"
    },
    {
        "text": "U xương là hiện tượng khối u phát triển bất thường bên trong xương do các tế bào phát triển không kiểm soát trong xương.",
        "head": "U xương",
        "head_type": "disease",
        "relation": "isSymptomOf",
        "tail": "Sự phát triển không kiểm soát của tế bào trong xương",
        "tail_type": "cause"
    },
    {
        "text": "Khối u tạo thành bên trong xương có thể ác tính liên quan đến ung thư xương hoặc là lành tính.",
        "head": "Khối u",
        "head_type": "disease",
        "relation": "relatedTo",
        "tail": "Ung thư xương",
        "tail_type": "disease"
    },
    {
        "text": "Mặt khác, u xương cũng có thể là một loại biến chứng di căn của các bệnh lý cơ xương khớp khác.",
        "head": "U xương",
        "head_type": "disease",
        "relation": "causedBy",
        "tail": "Bệnh lý cơ xương khớp",
        "tail_type": "disease"
    },
    {
        "text": "Và trong trường hợp khối u xương do di căn thì luôn là khối u ác tính, dẫn đến ung thư xương.",
        "head": "Khối u xương do di căn",
        "head_type": "disease",
        "relation": "relatedTo",
        "tail": "Ung thư xương",
        "tail_type": "disease"
    },
    {
        "text": "Bệnh có thể xảy ra ở cả trẻ em và người lớn tuổi.",
        "head": "U xương",
        "head_type": "disease",
        "relation": "affects",
        "tail": "Trẻ em",
        "tail_type": "lifestyle"
    },
    {
        "text": "Bệnh có thể xảy ra ở cả trẻ em và người lớn tuổi.",
        "head": "U xương",
        "head_type": "disease",
        "relation": "affects",
        "tail": "Người lớn tuổi",
        "tail_type": "lifestyle"
    },
    {
        "text": "Tuy nhiên, sự tiến triển của bệnh ở hai nhóm khác nhau.",
        "head": "U xương",
        "head_type": "disease",
        "relation": "affects",
        "tail": "Sự tiến triển của bệnh",
        "tail_type": "symptom"
    },
    {
        "text": "Ở trẻ em, phần lớn các trường hợp khối u ở xương đều là nguyên phát, khả năng liên quan đến ung thư khá thấp.",
        "head": "Khối u ở xương",
        "head_type": "disease",
        "relation": "relatedTo",
        "tail": "Ung thư",
        "tail_type": "disease"
    },
    {
        "text": "Người lớn, đặc biệt là người lớn tuổi, hầu hết các khối u xương ung thư đều là di căn.",
        "head": "Khối u xương ung thư",
        "head_type": "disease",
        "relation": "relatedTo",
        "tail": "Di căn",
        "tail_type": "cause"
    },
    {
        "text": "Tuy nhiên, các trường hợp u xương nguyên phát dẫn đến ung thư ít gặp.",
        "head": "U xương nguyên phát",
        "head_type": "disease",
        "relation": "relatedTo",
        "tail": "Ung thư",
        "tail_type": "disease"
    },
    {
        "text": "Số trường hợp u xương nguyên phát gây ung thư chỉ chiếm khoảng 3900 người mỗi năm ở Hoa Kỳ, được thống kê vào năm 2022 bởi Cẩm nang Y khoa MSD Manual Hoa Kỳ.",
        "head": "U xương nguyên phát gây ung thư",
        "head_type": "disease",
        "relation": "relatedTo",
        "tail": "Ung thư",
        "tail_type": "disease"
    },
    {
        "text": "Dù là u ác tính hay lành tính, người bệnh sẽ trải qua những cơn đau xương không rõ nguyên nhân, cường độ cơn đau tăng dần theo thời gian nếu không điều trị kịp thời.",
        "head": "U ác tính",
        "head_type": "disease",
        "relation": "isSymptomOf",
        "tail": "Đau xương",
        "tail_type": "symptom"
    },
    {
        "text": "Dù là u ác tính hay lành tính, người bệnh sẽ trải qua những cơn đau xương không rõ nguyên nhân, cường độ cơn đau tăng dần theo thời gian nếu không điều trị kịp thời.",
        "head": "U lành tính",
        "head_type": "disease",
        "relation": "isSymptomOf",
        "tail": "Đau xương",
        "tail_type": "symptom"
    },
    {
        "text": "Tình trạng bệnh nghiêm trọng hơn khi người bệnh đồng thời phát các triệu chứng sưng tấy tại vị trí có khối u và dễ gãy xương hơn bình thường.",
        "head": "U xương",
        "head_type": "disease",
        "relation": "isSymptomOf",
        "tail": "Sưng tấy",
        "tail_type": "symptom"
    },
    {
        "text": "Tình trạng bệnh nghiêm trọng hơn khi người bệnh đồng thời phát các triệu chứng sưng tấy tại vị trí có khối u và dễ gãy xương hơn bình thường.",
        "head": "U xương",
        "head_type": "disease",
        "relation": "isSymptomOf",
        "tail": "Gãy xương",
        "tail_type": "symptom"
    },
    {
        "text": "U xương sụn là loại u lành tính phổ biến nhất, chiếm khoảng 40% các trường hợp u xương lành tính.",
        "head": "U xương sụn",
        "head_type": "disease",
        "relation": "relatedTo",
        "tail": "U xương lành tính",
        "tail_type": "disease"
    },
    {
        "text": "Tình trạng u xương sụn là do sự bất thường tăng trưởng của sụn và xương, cụ thể là tăng trưởng quá nhiều.",
        "head": "U xương sụn",
        "head_type": "disease",
        "relation": "causedBy",
        "tail": "Sự bất thường tăng trưởng của sụn và xương",
        "tail_type": "cause"
    },
    {
        "text": "Chính vì thế mà bệnh thường xảy ra với những người nằm trong độ tuổi phát triển, từ 13 - 25 tuổi.",
        "head": "U xương sụn",
        "head_type": "disease",
        "relation": "affects",
        "tail": "Độ tuổi phát triển",
        "tail_type": "lifestyle"
    },
    {
        "text": "Thống kê của Học viện Phẫu thuật Chỉnh hình Hoa Kỳ (AAOS) cũng kết luận u xương sụn thường rơi vào những trường hợp trẻ em vị thành niên và thanh niên.",
        "head": "U xương sụn",
        "head_type": "disease",
        "relation": "affects",
        "tail": "Trẻ em vị thành niên và thanh niên",
        "tail_type": "lifestyle"
    },
    {
        "text": "Các khối u ở xương sụn hình thành ở vị trí đầu xương dài như xương cánh tay hoặc xương chân.",
        "head": "Khối u ở xương sụn",
        "head_type": "disease",
        "relation": "locatedIn",
        "tail": "Đầu xương dài",
        "tail_type": "organ"
    },
    {
        "text": "Các khối u ở xương sụn hình thành ở vị trí đầu xương dài như xương cánh tay hoặc xương chân.",
        "head": "Khối u ở xương sụn",
        "head_type": "disease",
        "relation": "locatedIn",
        "tail": "Xương cánh tay",
        "tail_type": "organ"
    },
    {
        "text": "Các khối u ở xương sụn hình thành ở vị trí đầu xương dài như xương cánh tay hoặc xương chân.",
        "head": "Khối u ở xương sụn",
        "head_type": "disease",
        "relation": "locatedIn",
        "tail": "Xương chân",
        "tail_type": "organ"
    },
    {
        "text": "U xơ không cốt hóa là một loại u xương, hình thành do sự tổn thương xơ hóa của xương với triệu chứng cận lâm sàng là tiêu vỏ xương có xuất hiện tổn thương.",
        "head": "U xơ không cốt hóa",
        "head_type": "disease",
        "relation": "isSymptomOf",
        "tail": "Sự tổn thương xơ hóa của xương",
        "tail_type": "cause"
    },
    {
        "text": "U xơ không cốt hóa là một loại u xương, hình thành do sự tổn thương xơ hóa của xương với triệu chứng cận lâm sàng là tiêu vỏ xương có xuất hiện tổn thương.",
        "head": "U xơ không cốt hóa",
        "head_type": "disease",
        "relation": "isSymptomOf",
        "tail": "Tiêu vỏ xương",
        "tail_type": "symptom"
    },
    {
        "text": "Đây là loại u lành tính.",
        "head": "U xơ không cốt hóa",
        "head_type": "disease",
        "relation": "relatedTo",
        "tail": "U lành tính",
        "tail_type": "disease"
    },
    {
        "text": "Người bị u xơ không cốt hóa sẽ có những ổ khuyết khá nhỏ bên trong xương.",
        "head": "U xơ không cốt hóa",
        "head_type": "disease",
        "relation": "isSymptomOf",
        "tail": "Ổ khuyết",
        "tail_type": "symptom"
    },
    {
        "text": "Những ổ khuyết này sẽ được lấp đầy bằng mô xơ thay vì mô xương như người khỏe mạnh.",
        "head": "Ổ khuyết",
        "head_type": "symptom",
        "relation": "relatedTo",
        "tail": "Mô xơ",
        "tail_type": "organ"
    },
    {
        "text": "Những ổ khuyết này sẽ được lấp đầy bằng mô xơ thay vì mô xương như người khỏe mạnh.",
        "head": "Ổ khuyết",
        "head_type": "symptom",
        "relation": "relatedTo",
        "tail": "Mô xương",
        "tail_type": "organ"
    },
    {
        "text": "U tế bào khổng lồ còn được gọi là u đại bào hoặc u hủy cốt bào, là một trong những kiểu u lành tính phổ biến.",
        "head": "U tế bào khổng lồ",
        "head_type": "disease",
        "relation": "relatedTo",
        "tail": "U lành tính",
        "tail_type": "disease"
    },
    {
        "text": "U tế bào khổng lồ còn được gọi là u đại bào hoặc u hủy cốt bào, là một trong những kiểu u lành tính phổ biến.",
        "head": "U tế bào khổng lồ",
        "head_type": "disease",
        "relation": "relatedTo",
        "tail": "U đại bào",
        "tail_type": "disease"
    },
    {
        "text": "U tế bào khổng lồ còn được gọi là u đại bào hoặc u hủy cốt bào, là một trong những kiểu u lành tính phổ biến.",
        "head": "U tế bào khổng lồ",
        "head_type": "disease",
        "relation": "relatedTo",
        "tail": "U hủy cốt bào",
        "tail_type": "disease"
    },
    {
        "text": "Tuy nhiên, bệnh có thể tiến triển thanh u tế bào khổng lồ ác tính, vì thế yêu cầu người bệnh cần có sự chú tâm điều trị bệnh hơn các u loại u xương lành tính khác.",
        "head": "U tế bào khổng lồ",
        "head_type": "disease",
        "relation": "relatedTo",
        "tail": "U tế bào khổng lồ ác tính",
        "tail_type": "disease"
    },
    {
        "text": "U tế bào khổng lồ diễn ra ở vị trí đầu xương dài, thường gặp là đầu trên xương chày, xương đùi, xương quay và đầu dưới xương cùng.",
        "head": "U tế bào khổng lồ",
        "head_type": "disease",
        "relation": "locatedIn",
        "tail": "Đầu xương dài",
        "tail_type": "organ"
    },
    {
        "text": "U tế bào khổng lồ diễn ra ở vị trí đầu xương dài, thường gặp là đầu trên xương chày, xương đùi, xương quay và đầu dưới xương cùng.",
        "head": "U tế bào khổng lồ",
        "head_type": "disease",
        "relation": "locatedIn",
        "tail": "Đầu trên xương chày",
        "tail_type": "organ"
    },
    {
        "text": "U tế bào khổng lồ diễn ra ở vị trí đầu xương dài, thường gặp là đầu trên xương chày, xương đùi, xương quay và đầu dưới xương cùng.",
        "head": "U tế bào khổng lồ",
        "head_type": "disease",
        "relation": "locatedIn",
        "tail": "Xương đùi",
        "tail_type": "organ"
    },
    {
        "text": "U tế bào khổng lồ diễn ra ở vị trí đầu xương dài, thường gặp là đầu trên xương chày, xương đùi, xương quay và đầu dưới xương cùng.",
        "head": "U tế bào khổng lồ",
        "head_type": "disease",
        "relation": "locatedIn",
        "tail": "Xương quay",
        "tail_type": "organ"
    },
    {
        "text": "U tế bào khổng lồ diễn ra ở vị trí đầu xương dài, thường gặp là đầu trên xương chày, xương đùi, xương quay và đầu dưới xương cùng.",
        "head": "U tế bào khổng lồ",
        "head_type": "disease",
        "relation": "locatedIn",
        "tail": "Đầu dưới xương cùng",
        "tail_type": "organ"
    },
    {
        "text": "Bệnh gồm 3 giai đoạn:  U nhỏ lành tính, vỏ xương bị phá hủy.",
        "head": "U tế bào khổng lồ",
        "head_type": "disease",
        "relation": "isSymptomOf",
        "tail": "U nhỏ lành tính",
        "tail_type": "disease"
    },
    {
        "text": "Bệnh gồm 3 giai đoạn:  U nhỏ lành tính, vỏ xương bị phá hủy.",
        "head": "U tế bào khổng lồ",
        "head_type": "disease",
        "relation": "isSymptomOf",
        "tail": "Vỏ xương bị phá hủy",
        "tail_type": "symptom"
    },
    {
        "text": "U tăng kích thước, vỏ xương bị tổn thương và mỏng hơn bình thường",
        "head": "U tế bào khổng lồ",
        "head_type": "disease",
        "relation": "isSymptomOf",
        "tail": "U tăng kích thước",
        "tail_type": "symptom"
    },
    {
        "text": "U tăng kích thước, vỏ xương bị tổn thương và mỏng hơn bình thường",
        "head": "U tế bào khổng lồ",
        "head_type": "disease",
        "relation": "isSymptomOf",
        "tail": "Vỏ xương bị tổn thương",
        "tail_type": "symptom"
    },
    {
        "text": "U tăng kích thước, vỏ xương bị tổn thương và mỏng hơn bình thường",
        "head": "U tế bào khổng lồ",
        "head_type": "disease",
        "relation": "isSymptomOf",
        "tail": "Vỏ xương mỏng",
        "tail_type": "symptom"
    },
    {
        "text": "U tăng sinh đáng kể, ảnh hưởng xấu đến các phần mềm xung quanh.",
        "head": "U tế bào khổng lồ",
        "head_type": "disease",
        "relation": "isSymptomOf",
        "tail": "U tăng sinh",
        "tail_type": "symptom"
    },
    {
        "text": "U tăng sinh đáng kể, ảnh hưởng xấu đến các phần mềm xung quanh.",
        "head": "U tế bào khổng lồ",
        "head_type": "disease",
        "relation": "affects",
        "tail": "Phần mềm xung quanh",
        "tail_type": "organ"
    },
    {
        "text": "Đồng thời mạch máu cũng tăng sinh nhiều.",
        "head": "U tế bào khổng lồ",
        "head_type": "disease",
        "relation": "isSymptomOf",
        "tail": "Mạch máu tăng sinh",
        "tail_type": "symptom"
    },
    {
        "text": "U sụn là tình trạng u nang sụn phát triển bên trong tủy xương, có các loại là u nguyên bào sụn, u xơ sụn và u nội sụn.",
        "head": "U sụn",
        "head_type": "disease",
        "relation": "isSymptomOf",
        "tail": "U nang sụn phát triển bên trong tủy xương",
        "tail_type": "cause"
    },
    {
        "text": "U sụn là tình trạng u nang sụn phát triển bên trong tủy xương, có các loại là u nguyên bào sụn, u xơ sụn và u nội sụn.",
        "head": "U sụn",
        "head_type": "disease",
        "relation": "relatedTo",
        "tail": "U nguyên bào sụn",
        "tail_type": "disease"
    },
    {
        "text": "U sụn là tình trạng u nang sụn phát triển bên trong tủy xương, có các loại là u nguyên bào sụn, u xơ sụn và u nội sụn.",
        "head": "U sụn",
        "head_type": "disease",
        "relation": "relatedTo",
        "tail": "U xơ sụn",
        "tail_type": "disease"
    },
    {
        "text": "U sụn là tình trạng u nang sụn phát triển bên trong tủy xương, có các loại là u nguyên bào sụn, u xơ sụn và u nội sụn.",
        "head": "U sụn",
        "head_type": "disease",
        "relation": "relatedTo",
        "tail": "U nội sụn",
        "tail_type": "disease"
    },
    {
        "text": "U nội sụn thường xảy ra như dạng u xương lành tính, trong khi u nguyên bào sụn tương đối hiếm gặp .",
        "head": "U nội sụn",
        "head_type": "disease",
        "relation": "relatedTo",
        "tail": "U xương lành tính",
        "tail_type": "disease"
    },
    {
        "text": "U nội sụn thường xảy ra như dạng u xương lành tính, trong khi u nguyên bào sụn tương đối hiếm gặp .",
        "head": "U nguyên bào sụn",
        "head_type": "disease",
        "relation": "relatedTo",
        "tail": "U xương lành tính",
        "tail_type": "disease"
    },
    {
        "text": "U nội sụn có thể xảy ra ở mọi lứa tuổi và đối tượng.",
        "head": "U nội sụn",
        "head_type": "disease",
        "relation": "affects",
        "tail": "Mọi lứa tuổi",
        "tail_type": "lifestyle"
    },
    {
        "text": "Bệnh thường không có các triệu chứng đi kèm, nhưng sự phát triển của khối u sẽ gây sưng và đau tại vị trí tổn thương.",
        "head": "U nội sụn",
        "head_type": "disease",
        "relation": "isSymptomOf",
        "tail": "Sưng",
        "tail_type": "symptom"
    },
    {
        "text": "Bệnh thường không có các triệu chứng đi kèm, nhưng sự phát triển của khối u sẽ gây sưng và đau tại vị trí tổn thương.",
        "head": "U nội sụn",
        "head_type": "disease",
        "relation": "isSymptomOf",
        "tail": "Đau",
        "tail_type": "symptom"
    },
    {
        "text": "Đây là một dạng khối u lành tính, tuy nhiên trong trường hợp người bệnh có nhiều khối u nội sụn, nhất là có xảy ra hiện tượng chảy máu mô mềm thì sẽ có nguy cơ mắc ung thư nội sụn cao hơn người khác.",
        "head": "U nội sụn",
        "head_type": "disease",
        "relation": "relatedTo",
        "tail": "Ung thư nội sụn",
        "tail_type": "disease"
    },
    {
        "text": "Nang xương phình mạch là sự tổn thương nang ở các vùng hành xương của xương dài, phần lớn xảy ra với những người trên 25 tuổi.",
        "head": "Nang xương phình mạch",
        "head_type": "disease",
        "relation": "isSymptomOf",
        "tail": "Tổn thương nang",
        "tail_type": "cause"
    },
    {
        "text": "Nang xương phình mạch là sự tổn thương nang ở các vùng hành xương của xương dài, phần lớn xảy ra với những người trên 25 tuổi.",
        "head": "Nang xương phình mạch",
        "head_type": "disease",
        "relation": "affects",
        "tail": "Hành xương",
        "tail_type": "organ"
    },
    {
        "text": "Nang xương phình mạch là sự tổn thương nang ở các vùng hành xương của xương dài, phần lớn xảy ra với những người trên 25 tuổi.",
        "head": "Nang xương phình mạch",
        "head_type": "disease",
        "relation": "affects",
        "tail": "Xương dài",
        "tail_type": "organ"
    },
    {
        "text": "Nang xương phình mạch là sự tổn thương nang ở các vùng hành xương của xương dài, phần lớn xảy ra với những người trên 25 tuổi.",
        "head": "Nang xương phình mạch",
        "head_type": "disease",
        "relation": "affects",
        "tail": "Người trên 25 tuổi",
        "tail_type": "lifestyle"
    },
    {
        "text": "Tổn thương do nang xương phình mạch có thể kéo dài từ vài tuần đến vài năm trước khi được chẩn đoán.",
        "head": "Tổn thương do nang xương phình mạch",
        "head_type": "disease",
        "relation": "isSymptomOf",
        "tail": "Kéo dài vài tuần",
        "tail_type": "symptom"
    },
    {
        "text": "Tổn thương do nang xương phình mạch có thể kéo dài từ vài tuần đến vài năm trước khi được chẩn đoán.",
        "head": "Tổn thương do nang xương phình mạch",
        "head_type": "disease",
        "relation": "isSymptomOf",
        "tail": "Kéo dài vài năm",
        "tail_type": "symptom"
    },
    {
        "text": "Các nang xương bị tổn thương có xu hướng phát triển chậm hơn bình thường, đồng thời xảy ra tình trạng phồng xương.",
        "head": "Nang xương bị tổn thương",
        "head_type": "disease",
        "relation": "isSymptomOf",
        "tail": "Phát triển chậm",
        "tail_type": "symptom"
    },
    {
        "text": "Ung thư xương tạo xương là một loại u xác tính, xảy ra khi các tế bào tạo ra khối u ác tính thay vì xương mới.",
        "head": "Ung thư xương tạo xương",
        "head_type": "disease",
        "relation": "isSymptomOf",
        "tail": "u xác tính",
        "tail_type": "disease"
    },
    {
        "text": "Ung thư xương tạo xương là một loại u xác tính, xảy ra khi các tế bào tạo ra khối u ác tính thay vì xương mới.",
        "head": "các tế bào tạo ra khối u ác tính",
        "head_type": "cause",
        "relation": "causes",
        "tail": "Ung thư xương tạo xương",
        "tail_type": "disease"
    },
    {
        "text": "Bệnh u xương ác tính này phần lớn xảy ra ở những vị trí xương đầu gối hoặc xương vai và các vùng xương dài.",
        "head": "Bệnh u xương ác tính",
        "head_type": "disease",
        "relation": "locatedIn",
        "tail": "xương đầu gối hoặc xương vai và các vùng xương dài",
        "tail_type": "organ"
    },
    {
        "text": "Người bệnh có những triệu chứng sưng đau quanh khu vực có khối u xương ác tính, cường độ cơn đau cao, có ảnh hưởng đến đi lại, sinh hoạt hằng ngày.",
        "head": "sưng đau quanh khu vực có khối u xương ác tính",
        "head_type": "symptom",
        "relation": "isSymptomOf",
        "tail": "Bệnh u xương ác tính",
        "tail_type": "disease"
    },
    {
        "text": "Người bệnh có những triệu chứng sưng đau quanh khu vực có khối u xương ác tính, cường độ cơn đau cao, có ảnh hưởng đến đi lại, sinh hoạt hằng ngày.",
        "head": "cường độ cơn đau cao",
        "head_type": "symptom",
        "relation": "isSymptomOf",
        "tail": "Bệnh u xương ác tính",
        "tail_type": "disease"
    },
    {
        "text": "Người bệnh có những triệu chứng sưng đau quanh khu vực có khối u xương ác tính, cường độ cơn đau cao, có ảnh hưởng đến đi lại, sinh hoạt hằng ngày.",
        "head": "ảnh hưởng đến đi lại, sinh hoạt hằng ngày",
        "head_type": "symptom",
        "relation": "isSymptomOf",
        "tail": "Bệnh u xương ác tính",
        "tail_type": "disease"
    },
    {
        "text": "Bệnh u xương ác tính, ung thư có tính chất gia đình Ewing Sarcoma thường gặp ở đối tượng thanh thiếu niên và thanh niên.",
        "head": "Bệnh u xương ác tính",
        "head_type": "disease",
        "relation": "associatedWith",
        "tail": "Ewing Sarcoma",
        "tail_type": "disease"
    },
    {
        "text": "Bệnh u xương ác tính, ung thư có tính chất gia đình Ewing Sarcoma thường gặp ở đối tượng thanh thiếu niên và thanh niên.",
        "head": "Ewing Sarcoma",
        "head_type": "disease",
        "relation": "associatedWith",
        "tail": "thanh thiếu niên và thanh niên",
        "tail_type": "lifestyle"
    },
    {
        "text": "Dù vậy, bệnh Sarcoma Ewing cũng có thể xảy ra ở trẻ em trên 5 tuổi.",
        "head": "Sarcoma Ewing",
        "head_type": "disease",
        "relation": "associatedWith",
        "tail": "trẻ em trên 5 tuổi",
        "tail_type": "lifestyle"
    },
    {
        "text": "Tế bào ung thư của Sarcoma Ewing xuất phát từ các hốc tủy, đó là phần hốc xương nơi tủy xương được tạo ra.",
        "head": "Tế bào ung thư của Sarcoma Ewing",
        "head_type": "cause",
        "relation": "causes",
        "tail": "Sarcoma Ewing",
        "tail_type": "disease"
    },
    {
        "text": "Tế bào ung thư của Sarcoma Ewing xuất phát từ các hốc tủy, đó là phần hốc xương nơi tủy xương được tạo ra.",
        "head": "Tế bào ung thư của Sarcoma Ewing",
        "head_type": "cause",
        "relation": "locatedIn",
        "tail": "các hốc tủy",
        "tail_type": "organ"
    },
    {
        "text": "Tế bào ung thư của Sarcoma Ewing xuất phát từ các hốc tủy, đó là phần hốc xương nơi tủy xương được tạo ra.",
        "head": "Tế bào ung thư của Sarcoma Ewing",
        "head_type": "cause",
        "relation": "locatedIn",
        "tail": "hốc xương",
        "tail_type": "organ"
    },
    {
        "text": "Ngoài ra Sarcoma Ewing cũng có thể phát triển trong các mô mềm như mỡ, cơ và mạch máu.",
        "head": "Sarcoma Ewing",
        "head_type": "disease",
        "relation": "locatedIn",
        "tail": "các mô mềm như mỡ, cơ và mạch máu",
        "tail_type": "organ"
    },
    {
        "text": "Bệnh Sarcoma sụn, còn được gọi là ung thư sụn, tiến triển từ những khối u xương ác tính phổ biến.",
        "head": "Bệnh Sarcoma sụn",
        "head_type": "disease",
        "relation": "isSymptomOf",
        "tail": "ung thư sụn",
        "tail_type": "disease"
    },
    {
        "text": "Bệnh Sarcoma sụn, còn được gọi là ung thư sụn, tiến triển từ những khối u xương ác tính phổ biến.",
        "head": "ung thư sụn",
        "head_type": "disease",
        "relation": "isSymptomOf",
        "tail": "khối u xương ác tính",
        "tail_type": "disease"
    },
    {
        "text": "Ung thư sụn thuộc loại ung thư nguyên phát, có tính phát triển và di căn, thường xảy ra ở xương chậu, hông và vai.",
        "head": "Ung thư sụn",
        "head_type": "disease",
        "relation": "locatedIn",
        "tail": "xương chậu, hông và vai",
        "tail_type": "organ"
    },
    {
        "text": "Ung thư sụn thuộc loại ung thư nguyên phát, có tính phát triển và di căn, thường xảy ra ở xương chậu, hông và vai.",
        "head": "Ung thư sụn",
        "head_type": "disease",
        "relation": "associatedWith",
        "tail": "di căn",
        "tail_type": "disease"
    },
    {
        "text": "Bệnh gồm 3 giai đoạn bệnh và nguy cơ di căn đến các cơ quan khác khá cao.",
        "head": "Bệnh",
        "head_type": "disease",
        "relation": "associatedWith",
        "tail": "di căn đến các cơ quan khác",
        "tail_type": "disease"
    },
    {
        "text": "Ung thư di căn xương là dạng ung thư thứ phát, xảy ra với những trường hợp đang có tế bào ung thư tại cơ quan khác.",
        "head": "Ung thư di căn xương",
        "head_type": "disease",
        "relation": "isSymptomOf",
        "tail": "ung thư thứ phát",
        "tail_type": "disease"
    },
    {
        "text": "Ung thư di căn xương là dạng ung thư thứ phát, xảy ra với những trường hợp đang có tế bào ung thư tại cơ quan khác.",
        "head": "tế bào ung thư tại cơ quan khác",
        "head_type": "cause",
        "relation": "causes",
        "tail": "Ung thư di căn xương",
        "tail_type": "disease"
    },
    {
        "text": "Bệnh có thể là biến chứng từ các ung thư như:  Ung thư thận Ung thư vú Ung thư tuyến tiền liệt Ung thư phổi Ung thư tuyến giáp",
        "head": "Bệnh",
        "head_type": "disease",
        "relation": "isSymptomOf",
        "tail": "Ung thư thận",
        "tail_type": "disease"
    },
    {
        "text": "Bệnh có thể là biến chứng từ các ung thư như:  Ung thư thận Ung thư vú Ung thư tuyến tiền liệt Ung thư phổi Ung thư tuyến giáp",
        "head": "Bệnh",
        "head_type": "disease",
        "relation": "isSymptomOf",
        "tail": "Ung thư vú",
        "tail_type": "disease"
    },
    {
        "text": "Bệnh có thể là biến chứng từ các ung thư như:  Ung thư thận Ung thư vú Ung thư tuyến tiền liệt Ung thư phổi Ung thư tuyến giáp",
        "head": "Bệnh",
        "head_type": "disease",
        "relation": "isSymptomOf",
        "tail": "Ung thư tuyến tiền liệt",
        "tail_type": "disease"
    },
    {
        "text": "Bệnh có thể là biến chứng từ các ung thư như:  Ung thư thận Ung thư vú Ung thư tuyến tiền liệt Ung thư phổi Ung thư tuyến giáp",
        "head": "Bệnh",
        "head_type": "disease",
        "relation": "isSymptomOf",
        "tail": "Ung thư phổi",
        "tail_type": "disease"
    },
    {
        "text": "Bệnh có thể là biến chứng từ các ung thư như:  Ung thư thận Ung thư vú Ung thư tuyến tiền liệt Ung thư phổi Ung thư tuyến giáp",
        "head": "Bệnh",
        "head_type": "disease",
        "relation": "isSymptomOf",
        "tail": "Ung thư tuyến giáp",
        "tail_type": "disease"
    },
    {
        "text": "Bệnh đa u tủy là ung thư của tương bào, phá hủy các xương xung quanh bằng cách xâm lấn và gây tổn thương chúng.",
        "head": "Bệnh đa u tủy",
        "head_type": "disease",
        "relation": "isSymptomOf",
        "tail": "ung thư của tương bào",
        "tail_type": "disease"
    },
    {
        "text": "Bệnh đa u tủy là ung thư của tương bào, phá hủy các xương xung quanh bằng cách xâm lấn và gây tổn thương chúng.",
        "head": "phá hủy các xương xung quanh",
        "head_type": "symptom",
        "relation": "isSymptomOf",
        "tail": "Bệnh đa u tủy",
        "tail_type": "disease"
    },
    {
        "text": "Bệnh gây ra các tình trạng tổn thương mỡ trong xương, gãy xương, suy thận hoặc nhiễm trùng.",
        "head": "tổn thương mỡ trong xương",
        "head_type": "symptom",
        "relation": "isSymptomOf",
        "tail": "Bệnh đa u tủy",
        "tail_type": "disease"
    },
    {
        "text": "Bệnh gây ra các tình trạng tổn thương mỡ trong xương, gãy xương, suy thận hoặc nhiễm trùng.",
        "head": "gãy xương",
        "head_type": "symptom",
        "relation": "isSymptomOf",
        "tail": "Bệnh đa u tủy",
        "tail_type": "disease"
    },
    {
        "text": "Bệnh gây ra các tình trạng tổn thương mỡ trong xương, gãy xương, suy thận hoặc nhiễm trùng.",
        "head": "suy thận",
        "head_type": "symptom",
        "relation": "isSymptomOf",
        "tail": "Bệnh đa u tủy",
        "tail_type": "disease"
    },
    {
        "text": "Bệnh gây ra các tình trạng tổn thương mỡ trong xương, gãy xương, suy thận hoặc nhiễm trùng.",
        "head": "nhiễm trùng",
        "head_type": "symptom",
        "relation": "isSymptomOf",
        "tail": "Bệnh đa u tủy",
        "tail_type": "disease"
    },
    {
        "text": "Những triệu chứng phổ biến ở bệnh u xương ác tính đa u tủy là đau xương dai dẳng, đặc biệt ở phần lưng và ngực.",
        "head": "đau xương dai dẳng",
        "head_type": "symptom",
        "relation": "isSymptomOf",
        "tail": "Bệnh đa u tủy",
        "tail_type": "disease"
    },
    {
        "text": "Những triệu chứng phổ biến ở bệnh u xương ác tính đa u tủy là đau xương dai dẳng, đặc biệt ở phần lưng và ngực.",
        "head": "đau xương dai dẳng",
        "head_type": "symptom",
        "relation": "locatedIn",
        "tail": "phần lưng và ngực",
        "tail_type": "organ"
    },
    {
        "text": "Nguyên nhân u xương ở người hiện nay vẫn chưa được xác định.",
        "head": "u xương",
        "head_type": "disease",
        "relation": "causedBy",
        "tail": "chưa được xác định",
        "tail_type": "cause"
    },
    {
        "text": "Có rất nhiều nguyên nhân thứ phát khiến xương phát triển khối u như xạ trị, tác dụng phụ của thuốc chống ung thư, tiền sử chấn thương xương, và di truyền.",
        "head": "xạ trị",
        "head_type": "cause",
        "relation": "causes",
        "tail": "khối u",
        "tail_type": "disease"
    },
    {
        "text": "Có rất nhiều nguyên nhân thứ phát khiến xương phát triển khối u như xạ trị, tác dụng phụ của thuốc chống ung thư, tiền sử chấn thương xương, và di truyền.",
        "head": "tác dụng phụ của thuốc chống ung thư",
        "head_type": "cause",
        "relation": "causes",
        "tail": "khối u",
        "tail_type": "disease"
    },
    {
        "text": "Có rất nhiều nguyên nhân thứ phát khiến xương phát triển khối u như xạ trị, tác dụng phụ của thuốc chống ung thư, tiền sử chấn thương xương, và di truyền.",
        "head": "tiền sử chấn thương xương",
        "head_type": "cause",
        "relation": "causes",
        "tail": "khối u",
        "tail_type": "disease"
    },
    {
        "text": "Có rất nhiều nguyên nhân thứ phát khiến xương phát triển khối u như xạ trị, tác dụng phụ của thuốc chống ung thư, tiền sử chấn thương xương, và di truyền.",
        "head": "di truyền",
        "head_type": "cause",
        "relation": "causes",
        "tail": "khối u",
        "tail_type": "disease"
    },
    {
        "text": "Với khối u lành tính, khối u xuất hiện phần lớn trong giai đoạn xương phát triển vượt trội nhất.",
        "head": "khối u lành tính",
        "head_type": "disease",
        "relation": "associatedWith",
        "tail": "giai đoạn xương phát triển vượt trội nhất",
        "tail_type": "lifestyle"
    },
    {
        "text": "Do vậy, độ tuổi có nguy cơ mắc u xương lành tính rơi vào nhóm đối tượng từ 10 - 20 tuổi.",
        "head": "u xương lành tính",
        "head_type": "disease",
        "relation": "associatedWith",
        "tail": "nhóm đối tượng từ 10 - 20 tuổi",
        "tail_type": "lifestyle"
    },
    {
        "text": "U xương ác tính hay ung thư xương có thể là ung thư nguyên phát hoặc do di căn.",
        "head": "U xương ác tính",
        "head_type": "disease",
        "relation": "isSymptomOf",
        "tail": "ung thư nguyên phát",
        "tail_type": "disease"
    },
    {
        "text": "U xương ác tính hay ung thư xương có thể là ung thư nguyên phát hoặc do di căn.",
        "head": "U xương ác tính",
        "head_type": "disease",
        "relation": "isSymptomOf",
        "tail": "di căn",
        "tail_type": "disease"
    },
    {
        "text": "U xương ác tính nguyên phát là do bên trong xương phát triển khối u ác tính, và nguyên nhân trực tiếp hình thành khối u vẫn chưa được xác định.",
        "head": "U xương ác tính nguyên phát",
        "head_type": "disease",
        "relation": "locatedIn",
        "tail": "bên trong xương",
        "tail_type": "organ"
    },
    {
        "text": "U xương ác tính nguyên phát là do bên trong xương phát triển khối u ác tính, và nguyên nhân trực tiếp hình thành khối u vẫn chưa được xác định.",
        "head": "khối u ác tính",
        "head_type": "cause",
        "relation": "causes",
        "tail": "U xương ác tính nguyên phát",
        "tail_type": "disease"
    },
    {
        "text": "Đối với khối u xương ác tính thứ phát, cũng là ung thư xương do di căn từ những bệnh lý khác như:  Ung thư vú Ung thư thận Ung thư phổi Ung thư tuyến tiền liệt Ung thư tuyến giáp",
        "head": "khối u xương ác tính thứ phát",
        "head_type": "disease",
        "relation": "isSymptomOf",
        "tail": "ung thư xương do di căn",
        "tail_type": "disease"
    },
    {
        "text": "Đối với khối u xương ác tính thứ phát, cũng là ung thư xương do di căn từ những bệnh lý khác như:  Ung thư vú Ung thư thận Ung thư phổi Ung thư tuyến tiền liệt Ung thư tuyến giáp",
        "head": "khối u xương ác tính thứ phát",
        "head_type": "disease",
        "relation": "isSymptomOf",
        "tail": "Ung thư vú",
        "tail_type": "disease"
    },
    {
        "text": "Đối với khối u xương ác tính thứ phát, cũng là ung thư xương do di căn từ những bệnh lý khác như:  Ung thư vú Ung thư thận Ung thư phổi Ung thư tuyến tiền liệt Ung thư tuyến giáp",
        "head": "khối u xương ác tính thứ phát",
        "head_type": "disease",
        "relation": "isSymptomOf",
        "tail": "Ung thư thận",
        "tail_type": "disease"
    },
    {
        "text": "Đối với khối u xương ác tính thứ phát, cũng là ung thư xương do di căn từ những bệnh lý khác như:  Ung thư vú Ung thư thận Ung thư phổi Ung thư tuyến tiền liệt Ung thư tuyến giáp",
        "head": "khối u xương ác tính thứ phát",
        "head_type": "disease",
        "relation": "isSymptomOf",
        "tail": "Ung thư phổi",
        "tail_type": "disease"
    },
    {
        "text": "Đối với khối u xương ác tính thứ phát, cũng là ung thư xương do di căn từ những bệnh lý khác như:  Ung thư vú Ung thư thận Ung thư phổi Ung thư tuyến tiền liệt Ung thư tuyến giáp",
        "head": "khối u xương ác tính thứ phát",
        "head_type": "disease",
        "relation": "isSymptomOf",
        "tail": "Ung thư tuyến tiền liệt",
        "tail_type": "disease"
    },
    {
        "text": "Đối với khối u xương ác tính thứ phát, cũng là ung thư xương do di căn từ những bệnh lý khác như:  Ung thư vú Ung thư thận Ung thư phổi Ung thư tuyến tiền liệt Ung thư tuyến giáp",
        "head": "khối u xương ác tính thứ phát",
        "head_type": "disease",
        "relation": "isSymptomOf",
        "tail": "Ung thư tuyến giáp",
        "tail_type": "disease"
    },
    {
        "text": "Khối u ở xương được nhận biết qua triệu chứng điển hình nhất là cơn đau âm ỉ quanh vùng có khối u.",
        "head": "cơn đau âm ỉ quanh vùng có khối u",
        "head_type": "symptom",
        "relation": "isSymptomOf",
        "tail": "khối u ở xương",
        "tail_type": "disease"
    },
    {
        "text": "Dù là u xương lành tính hay ác tính, người bệnh sẽ trải qua cảm giác đau tại vị trí tổn thương.",
        "head": "cảm giác đau tại vị trí tổn thương",
        "head_type": "symptom",
        "relation": "isSymptomOf",
        "tail": "u xương lành tính",
        "tail_type": "disease"
    },
    {
        "text": "Dù là u xương lành tính hay ác tính, người bệnh sẽ trải qua cảm giác đau tại vị trí tổn thương.",
        "head": "cảm giác đau tại vị trí tổn thương",
        "head_type": "symptom",
        "relation": "isSymptomOf",
        "tail": "u xương ác tính",
        "tail_type": "disease"
    },
    {
        "text": "Cường độ cơn đau sẽ tăng dần và nghiêm trọng hơn nếu bệnh kéo dài không điều trị, có thể ảnh hưởng đến sinh hoạt hàng ngày của người bệnh, thậm chí có thể đánh thức người bệnh lúc nửa đêm.",
        "head": "cường độ cơn đau sẽ tăng dần",
        "head_type": "symptom",
        "relation": "isSymptomOf",
        "tail": "u xương",
        "tail_type": "disease"
    },
    {
        "text": "Cường độ cơn đau sẽ tăng dần và nghiêm trọng hơn nếu bệnh kéo dài không điều trị, có thể ảnh hưởng đến sinh hoạt hàng ngày của người bệnh, thậm chí có thể đánh thức người bệnh lúc nửa đêm.",
        "head": "ảnh hưởng đến sinh hoạt hàng ngày",
        "head_type": "symptom",
        "relation": "isSymptomOf",
        "tail": "u xương",
        "tail_type": "disease"
    },
    {
        "text": "Cường độ cơn đau sẽ tăng dần và nghiêm trọng hơn nếu bệnh kéo dài không điều trị, có thể ảnh hưởng đến sinh hoạt hàng ngày của người bệnh, thậm chí có thể đánh thức người bệnh lúc nửa đêm.",
        "head": "đánh thức người bệnh lúc nửa đêm",
        "head_type": "symptom",
        "relation": "isSymptomOf",
        "tail": "u xương",
        "tail_type": "disease"
    },
    {
        "text": "Hầu hết, các cơn đau xảy ra khi người bệnh vận động mạnh, tạo áp lực lớn lên vị trí khối u như mang vác nặng.",
        "head": "các cơn đau",
        "head_type": "symptom",
        "relation": "aggravatedBy",
        "tail": "vận động mạnh",
        "tail_type": "lifestyle"
    },
    {
        "text": "Hầu hết, các cơn đau xảy ra khi người bệnh vận động mạnh, tạo áp lực lớn lên vị trí khối u như mang vác nặng.",
        "head": "các cơn đau",
        "head_type": "symptom",
        "relation": "aggravatedBy",
        "tail": "mang vác nặng",
        "tail_type": "lifestyle"
    },
    {
        "text": "U xương ác tính sẽ có triệu chứng từ cơn đau tăng dần theo thời gian, bên cạnh đó, xương cũng sẽ trở nên yếu dần.",
        "head": "cơn đau tăng dần theo thời gian",
        "head_type": "symptom",
        "relation": "isSymptomOf",
        "tail": "U xương ác tính",
        "tail_type": "disease"
    },
    {
        "text": "U xương ác tính sẽ có triệu chứng từ cơn đau tăng dần theo thời gian, bên cạnh đó, xương cũng sẽ trở nên yếu dần.",
        "head": "xương yếu dần",
        "head_type": "symptom",
        "relation": "isSymptomOf",
        "tail": "U xương ác tính",
        "tail_type": "disease"
    },
    {
        "text": "Điều này khiến người bệnh đối mặt với nguy cơ gãy xương cao, kể cả trong những trường hợp chấn thương nhẹ.",
        "head": "gãy xương",
        "head_type": "symptom",
        "relation": "isSymptomOf",
        "tail": "U xương ác tính",
        "tail_type": "disease"
    },
    {
        "text": "Tuy nhiên, những trường hợp u xương lành tính có thể không gây ra bất cứ triệu chứng nào.",
        "head": "u xương lành tính",
        "head_type": "disease",
        "relation": "associatedWith",
        "tail": "không gây ra bất cứ triệu chứng nào",
        "tail_type": "symptom"
    },
    {
        "text": "Vì thế, nếu u xương không gây ra triệu chứng, khối u không gây cản trở đến hoạt động và vận động hàng ngày, người bệnh sẽ khó có thể nhận biết được mình đang mắc bệnh nếu như không đi thực hiện các xét nghiệm cận lâm sàng.",
        "head": "u xương",
        "head_type": "disease",
        "relation": "associatedWith",
        "tail": "không gây ra triệu chứng",
        "tail_type": "symptom"
    },
    {
        "text": "Vì thế, nếu u xương không gây ra triệu chứng, khối u không gây cản trở đến hoạt động và vận động hàng ngày, người bệnh sẽ khó có thể nhận biết được mình đang mắc bệnh nếu như không đi thực hiện các xét nghiệm cận lâm sàng.",
        "head": "khối u",
        "head_type": "disease",
        "relation": "associatedWith",
        "tail": "không gây cản trở đến hoạt động và vận động hàng ngày",
        "tail_type": "symptom"
    },
    {
        "text": "Chẩn đoán bệnh u xương bắt đầu với việc thu thập các triệu chứng lâm sàng của người bệnh để có thể loại trừ các bệnh lý khác như gãy xương, nhiễm trùng,&#8230; Bác sĩ sẽ chỉ định người bệnh thực hiện các phương pháp chẩn đoán cận lâm sàng tiếp theo đó để thu thập kết quả hình ảnh nhằm chẩn đoán rõ hơn về tình trạng khối u xương.",
        "head": "Chẩn đoán bệnh u xương",
        "head_type": "disease",
        "relation": "diagnosedBy",
        "tail": "thu thập các triệu chứng lâm sàng",
        "tail_type": "symptom"
    },
    {
        "text": "Chẩn đoán bệnh u xương bắt đầu với việc thu thập các triệu chứng lâm sàng của người bệnh để có thể loại trừ các bệnh lý khác như gãy xương, nhiễm trùng,&#8230; Bác sĩ sẽ chỉ định người bệnh thực hiện các phương pháp chẩn đoán cận lâm sàng tiếp theo đó để thu thập kết quả hình ảnh nhằm chẩn đoán rõ hơn về tình trạng khối u xương.",
        "head": "Chẩn đoán bệnh u xương",
        "head_type": "disease",
        "relation": "diagnosedBy",
        "tail": "các phương pháp chẩn đoán cận lâm sàng",
        "tail_type": "test"
    },
    {
        "text": "Chẩn đoán bệnh u xương bắt đầu với việc thu thập các triệu chứng lâm sàng của người bệnh để có thể loại trừ các bệnh lý khác như gãy xương, nhiễm trùng,&#8230; Bác sĩ sẽ chỉ định người bệnh thực hiện các phương pháp chẩn đoán cận lâm sàng tiếp theo đó để thu thập kết quả hình ảnh nhằm chẩn đoán rõ hơn về tình trạng khối u xương.",
        "head": "Chẩn đoán bệnh u xương",
        "head_type": "disease",
        "relation": "diagnosedBy",
        "tail": "thu thập kết quả hình ảnh",
        "tail_type": "test"
    },
    {
        "text": "Đầu tiên, bác sĩ sẽ kiểm tra vùng nghi ngờ có khối u. Đồng thời, đánh giá tình trạng độ mềm trong xương người bệnh và phạm vi vận động.",
        "head": "kiểm tra vùng nghi ngờ có khối u",
        "head_type": "test",
        "relation": "diagnosedBy",
        "tail": "bệnh u xương",
        "tail_type": "disease"
    },
    {
        "text": "Đầu tiên, bác sĩ sẽ kiểm tra vùng nghi ngờ có khối u. Đồng thời, đánh giá tình trạng độ mềm trong xương người bệnh và phạm vi vận động.",
        "head": "đánh giá tình trạng độ mềm trong xương",
        "head_type": "test",
        "relation": "diagnosedBy",
        "tail": "bệnh u xương",
        "tail_type": "disease"
    },
    {
        "text": "Đầu tiên, bác sĩ sẽ kiểm tra vùng nghi ngờ có khối u. Đồng thời, đánh giá tình trạng độ mềm trong xương người bệnh và phạm vi vận động.",
        "head": "đánh giá phạm vi vận động",
        "head_type": "test",
        "relation": "diagnosedBy",
        "tail": "bệnh u xương",
        "tail_type": "disease"
    },
    {
        "text": "Tiếp theo, người bệnh sẽ thực hiện các bước cần thiết như xét nghiệm máu và nước tiểu trước khi đi xét nghiệm chẩn đoán chuyên sâu.",
        "head": "xét nghiệm máu",
        "head_type": "test",
        "relation": "diagnosedBy",
        "tail": "bệnh u xương",
        "tail_type": "disease"
    },
    {
        "text": "Tiếp theo, người bệnh sẽ thực hiện các bước cần thiết như xét nghiệm máu và nước tiểu trước khi đi xét nghiệm chẩn đoán chuyên sâu.",
        "head": "xét nghiệm nước tiểu",
        "head_type": "test",
        "relation": "diagnosedBy",
        "tail": "bệnh u xương",
        "tail_type": "disease"
    },
    {
        "text": "Những phương pháp chẩn đoán bệnh u xương được sử dụng nhiều gồm:  Chụp x-quang Chụp cắt lớp vi tính CT Chụp MRI Sinh thiết khối u Sinh thiết mở",
        "head": "Chụp x-quang",
        "head_type": "test",
        "relation": "diagnosedBy",
        "tail": "bệnh u xương",
        "tail_type": "disease"
    },
    {
        "text": "Những phương pháp chẩn đoán bệnh u xương được sử dụng nhiều gồm:  Chụp x-quang Chụp cắt lớp vi tính CT Chụp MRI Sinh thiết khối u Sinh thiết mở",
        "head": "Chụp cắt lớp vi tính CT",
        "head_type": "test",
        "relation": "diagnosedBy",
        "tail": "bệnh u xương",
        "tail_type": "disease"
    },
    {
        "text": "Những phương pháp chẩn đoán bệnh u xương được sử dụng nhiều gồm:  Chụp x-quang Chụp cắt lớp vi tính CT Chụp MRI Sinh thiết khối u Sinh thiết mở",
        "head": "Chụp MRI",
        "head_type": "test",
        "relation": "diagnosedBy",
        "tail": "bệnh u xương",
        "tail_type": "disease"
    },
    {
        "text": "Những phương pháp chẩn đoán bệnh u xương được sử dụng nhiều gồm:  Chụp x-quang Chụp cắt lớp vi tính CT Chụp MRI Sinh thiết khối u Sinh thiết mở",
        "head": "Sinh thiết khối u",
        "head_type": "test",
        "relation": "diagnosedBy",
        "tail": "bệnh u xương",
        "tail_type": "disease"
    },
    {
        "text": "Những phương pháp chẩn đoán bệnh u xương được sử dụng nhiều gồm:  Chụp x-quang Chụp cắt lớp vi tính CT Chụp MRI Sinh thiết khối u Sinh thiết mở",
        "head": "Sinh thiết mở",
        "head_type": "test",
        "relation": "diagnosedBy",
        "tail": "bệnh u xương",
        "tail_type": "disease"
    },
    {
        "text": "Biến chứng u xương sẽ xảy ra với trường hợp u ác tính, ung thư xương.",
        "head": "Biến chứng u xương",
        "head_type": "disease",
        "relation": "isSymptomOf",
        "tail": "u ác tính",
        "tail_type": "disease"
    },
    {
        "text": "Biến chứng u xương sẽ xảy ra với trường hợp u ác tính, ung thư xương.",
        "head": "Biến chứng u xương",
        "head_type": "disease",
        "relation": "isSymptomOf",
        "tail": "ung thư xương",
        "tail_type": "disease"
    },
    {
        "text": "Bệnh phát triển các biến chứng sẽ khiến người bệnh đối mặt với rủi ro bị tàn phế, mất chức năng chi thể.",
        "head": "Biến chứng",
        "head_type": "disease",
        "relation": "affects",
        "tail": "chức năng chi thể",
        "tail_type": "organ"
    },
    {
        "text": "Đặc biệt, ung thư xương sẽ có thể gây ra di căn đến khắp cơ thể và phá huỷ các mô xương bình thường.",
        "head": "ung thư xương",
        "head_type": "disease",
        "relation": "affects",
        "tail": "các mô xương bình thường",
        "tail_type": "organ"
    },
    {
        "text": "U xương lành tính hầu như không gây ra biến chứng gì đáng lo ngại vì vốn bệnh cũng không có triệu chứng nguy hiểm cho sức khỏe người bệnh.",
        "head": "U xương lành tính",
        "head_type": "disease",
        "relation": "isSymptomOf",
        "tail": "không có triệu chứng nguy hiểm",
        "tail_type": "symptom"
    },
    {
        "text": "Dù vậy, người bệnh có thể sẽ bị yếu xương hơn bình thường do bị ảnh hưởng của khối u.",
        "head": "yếu xương",
        "head_type": "symptom",
        "relation": "isSymptomOf",
        "tail": "khối u",
        "tail_type": "disease"
    },
    {
        "text": "U xương lành tính không nhất thiết điều trị nếu người bệnh không bị triệu chứng bệnh cản trở các hoạt động và vận động thường ngày.",
        "head": "U xương lành tính",
        "head_type": "disease",
        "relation": "treatedBy",
        "tail": "điều trị",
        "tail_type": "treatment"
    },
    {
        "text": "Thông thường, khối u lành tính sẽ tiêu biến dần theo thời gian.",
        "head": "khối u lành tính",
        "head_type": "disease",
        "relation": "treatedBy",
        "tail": "tiêu biến dần theo thời gian",
        "tail_type": "treatment"
    },
    {
        "text": "Tuy nhiên có những trường hợp khối u không biến mất hoặc phát triển to hơn.",
        "head": "khối u",
        "head_type": "disease",
        "relation": "isSymptomOf",
        "tail": "không biến mất",
        "tail_type": "symptom"
    },
    {
        "text": "Tuy nhiên có những trường hợp khối u không biến mất hoặc phát triển to hơn.",
        "head": "khối u",
        "head_type": "disease",
        "relation": "isSymptomOf",
        "tail": "phát triển to hơn",
        "tail_type": "symptom"
    },
    {
        "text": "Lúc này, bác sĩ sẽ xem xét và chỉ định người bệnh phẫu thuật cắt bỏ khối u để tránh tình trạng lan rộng khối u hoặc biến đổi thành khối u ác tính, nguy hiểm đến tính mạng người bệnh.",
        "head": "phẫu thuật cắt bỏ khối u",
        "head_type": "treatment",
        "relation": "treatedBy",
        "tail": "khối u",
        "tail_type": "disease"
    },
    {
        "text": "Lúc này, bác sĩ sẽ xem xét và chỉ định người bệnh phẫu thuật cắt bỏ khối u để tránh tình trạng lan rộng khối u hoặc biến đổi thành khối u ác tính, nguy hiểm đến tính mạng người bệnh.",
        "head": "phẫu thuật cắt bỏ khối u",
        "head_type": "treatment",
        "relation": "preventedBy",
        "tail": "lan rộng khối u",
        "tail_type": "disease"
    },
    {
        "text": "Lúc này, bác sĩ sẽ xem xét và chỉ định người bệnh phẫu thuật cắt bỏ khối u để tránh tình trạng lan rộng khối u hoặc biến đổi thành khối u ác tính, nguy hiểm đến tính mạng người bệnh.",
        "head": "phẫu thuật cắt bỏ khối u",
        "head_type": "treatment",
        "relation": "preventedBy",
        "tail": "biến đổi thành khối u ác tính",
        "tail_type": "disease"
    },
    {
        "text": "Phương pháp điều trị u xương ác tính phụ thuộc vào loại u xương hoặc ung thư xương của người bệnh.",
        "head": "Phương pháp điều trị u xương ác tính",
        "head_type": "treatment",
        "relation": "treatedBy",
        "tail": "u xương ác tính",
        "tail_type": "disease"
    },
    {
        "text": "Phương pháp điều trị u xương ác tính phụ thuộc vào loại u xương hoặc ung thư xương của người bệnh.",
        "head": "Phương pháp điều trị u xương ác tính",
        "head_type": "treatment",
        "relation": "treatedBy",
        "tail": "ung thư xương",
        "tail_type": "disease"
    },
    {
        "text": "Ngoài ra, phác đồ điều trị cũng cần phải đánh giá về tình trạng di căn của tế bào ung thư, vị trí phát triển tế bào.",
        "head": "phác đồ điều trị",
        "head_type": "treatment",
        "relation": "treatedBy",
        "tail": "di căn của tế bào ung thư",
        "tail_type": "disease"
    },
    {
        "text": "Quá trình điều trị sẽ khó khăn hơn nếu u xương ác tính đã tiến đến giai đoạn di căn.",
        "head": "Quá trình điều trị",
        "head_type": "treatment",
        "relation": "treatedBy",
        "tail": "u xương ác tính",
        "tail_type": "disease"
    },
    {
        "text": "Quá trình điều trị sẽ khó khăn hơn nếu u xương ác tính đã tiến đến giai đoạn di căn.",
        "head": "Quá trình điều trị",
        "head_type": "treatment",
        "relation": "aggravatedBy",
        "tail": "di căn",
        "tail_type": "disease"
    },
    {
        "text": "Những phương pháp điều trị u xương ác tính, ung thư xương gồm:  Phẫu thuật loại bỏ hoàn toàn khối u Xạ trị, thường được kết hợp với việc phẫu thuật để thu nhỏ khối u trước khi phẫu thuật.",
        "head": "Phẫu thuật loại bỏ hoàn toàn khối u",
        "head_type": "treatment",
        "relation": "treatedBy",
        "tail": "u xương ác tính",
        "tail_type": "disease"
    },
    {
        "text": "Những phương pháp điều trị u xương ác tính, ung thư xương gồm:  Phẫu thuật loại bỏ hoàn toàn khối u Xạ trị, thường được kết hợp với việc phẫu thuật để thu nhỏ khối u trước khi phẫu thuật.",
        "head": "Phẫu thuật loại bỏ hoàn toàn khối u",
        "head_type": "treatment",
        "relation": "treatedBy",
        "tail": "ung thư xương",
        "tail_type": "disease"
    },
    {
        "text": "Những phương pháp điều trị u xương ác tính, ung thư xương gồm:  Phẫu thuật loại bỏ hoàn toàn khối u Xạ trị, thường được kết hợp với việc phẫu thuật để thu nhỏ khối u trước khi phẫu thuật.",
        "head": "Xạ trị",
        "head_type": "treatment",
        "relation": "treatedBy",
        "tail": "u xương ác tính",
        "tail_type": "disease"
    },
    {
        "text": "Những phương pháp điều trị u xương ác tính, ung thư xương gồm:  Phẫu thuật loại bỏ hoàn toàn khối u Xạ trị, thường được kết hợp với việc phẫu thuật để thu nhỏ khối u trước khi phẫu thuật.",
        "head": "Xạ trị",
        "head_type": "treatment",
        "relation": "treatedBy",
        "tail": "ung thư xương",
        "tail_type": "disease"
    },
    {
        "text": "Ngoài ra, xạ trị cũng được áp dụng để tiêu diệt tế bào ung thư",
        "head": "Xạ trị",
        "head_type": "treatment",
        "relation": "treatedBy",
        "tail": "tế bào ung thư",
        "tail_type": "disease"
    },
    {
        "text": "Hóa trị để tiêu diệt tế bào ung thư đang phát triển hoặc có khả năng di căn cao",
        "head": "Hóa trị",
        "head_type": "treatment",
        "relation": "treatedBy",
        "tail": "tế bào ung thư",
        "tail_type": "disease"
    },
    {
        "text": "Hóa trị để tiêu diệt tế bào ung thư đang phát triển hoặc có khả năng di căn cao",
        "head": "Hóa trị",
        "head_type": "treatment",
        "relation": "preventedBy",
        "tail": "di căn",
        "tail_type": "disease"
    },
    {
        "text": "Phẫu thuật lạnh, loại bỏ tế bào ung thư bằng nitơ lỏng",
        "head": "Phẫu thuật lạnh",
        "head_type": "treatment",
        "relation": "treatedBy",
        "tail": "tế bào ung thư",
        "tail_type": "disease"
    },
    {
        "text": "Cần lưu ý một số tác dụng phụ mà người bệnh có thể gặp phải khi thực hiện hóa trị, xạ trị để điều trị u xương ác tính.",
        "head": "Hóa trị",
        "head_type": "treatment",
        "relation": "isSymptomOf",
        "tail": "tác dụng phụ",
        "tail_type": "symptom"
    },
    {
        "text": "Cần lưu ý một số tác dụng phụ mà người bệnh có thể gặp phải khi thực hiện hóa trị, xạ trị để điều trị u xương ác tính.",
        "head": "Xạ trị",
        "head_type": "treatment",
        "relation": "isSymptomOf",
        "tail": "tác dụng phụ",
        "tail_type": "symptom"
    },
    {
        "text": "Những tác dụng phục gồm:  Buồn nôn Cáu gắt Rụng tóc Suy nhược cơ thể",
        "head": "Buồn nôn",
        "head_type": "symptom",
        "relation": "isSymptomOf",
        "tail": "Hóa trị",
        "tail_type": "treatment"
    },
    {
        "text": "Những tác dụng phục gồm:  Buồn nôn Cáu gắt Rụng tóc Suy nhược cơ thể",
        "head": "Buồn nôn",
        "head_type": "symptom",
        "relation": "isSymptomOf",
        "tail": "Xạ trị",
        "tail_type": "treatment"
    },
    {
        "text": "Những tác dụng phục gồm:  Buồn nôn Cáu gắt Rụng tóc Suy nhược cơ thể",
        "head": "Cáu gắt",
        "head_type": "symptom",
        "relation": "isSymptomOf",
        "tail": "Hóa trị",
        "tail_type": "treatment"
    },
    {
        "text": "Những tác dụng phục gồm:  Buồn nôn Cáu gắt Rụng tóc Suy nhược cơ thể",
        "head": "Cáu gắt",
        "head_type": "symptom",
        "relation": "isSymptomOf",
        "tail": "Xạ trị",
        "tail_type": "treatment"
    },
    {
        "text": "Những tác dụng phục gồm:  Buồn nôn Cáu gắt Rụng tóc Suy nhược cơ thể",
        "head": "Rụng tóc",
        "head_type": "symptom",
        "relation": "isSymptomOf",
        "tail": "Hóa trị",
        "tail_type": "treatment"
    },
    {
        "text": "Những tác dụng phục gồm:  Buồn nôn Cáu gắt Rụng tóc Suy nhược cơ thể",
        "head": "Rụng tóc",
        "head_type": "symptom",
        "relation": "isSymptomOf",
        "tail": "Xạ trị",
        "tail_type": "treatment"
    },
    {
        "text": "Những tác dụng phục gồm:  Buồn nôn Cáu gắt Rụng tóc Suy nhược cơ thể",
        "head": "Suy nhược cơ thể",
        "head_type": "symptom",
        "relation": "isSymptomOf",
        "tail": "Hóa trị",
        "tail_type": "treatment"
    },
    {
        "text": "Người bệnh sau điều trị u xương cần thực hiện đúng theo yêu cầu tái khám của bác sĩ, kết hợp với việc tự quản lý sức khỏe cơ thể của mình.",
        "head": "tái khám",
        "head_type": "treatment",
        "relation": "treatedBy",
        "tail": "u xương",
        "tail_type": "disease"
    },
    {
        "text": "Việc tái khám đúng hẹn với bác sĩ giúp người bệnh nắm rõ được tình trạng khối u trong cơ thể, cũng như kịp thời xử lý sớm những nguy cơ có thể gặp phải.",
        "head": "tái khám",
        "head_type": "treatment",
        "relation": "relatedTo",
        "tail": "khối u",
        "tail_type": "disease"
    },
    {
        "text": "Thời gian phục hồi sau điều trị phụ thuộc vào kích thước và vị trí khối u.",
        "head": "khối u",
        "head_type": "disease",
        "relation": "locatedIn",
        "tail": "cơ thể",
        "tail_type": "organ"
    },
    {
        "text": "Ngoài ra, người bệnh tuân thủ đúng những yêu cầu của bác sĩ, thực hiện lối sống khỏe mạnh cùng chế độ dinh dưỡng phù hợp cũng sẽ góp phần thúc đẩy quá trình hồi phục và hiệu quả của phác đồ.",
        "head": "lối sống khỏe mạnh",
        "head_type": "lifestyle",
        "relation": "relatedTo",
        "tail": "hồi phục",
        "tail_type": "treatment"
    },
    {
        "text": "U xương chưa có phương pháp ngăn ngừa hoàn toàn.",
        "head": "u xương",
        "head_type": "disease",
        "relation": "preventedBy",
        "tail": "ngăn ngừa",
        "tail_type": "treatment"
    },
    {
        "text": "Cách phòng ngừa bệnh tối ưu nhất là xây dựng một nền sức khỏe tổng thể tốt và nắm rõ tình trạng sức khỏe của chính mình.",
        "head": "sức khỏe tổng thể",
        "head_type": "lifestyle",
        "relation": "preventedBy",
        "tail": "u xương",
        "tail_type": "disease"
    },
    {
        "text": "Việc này không chỉ giúp bạn có thể giảm thiểu được rủi ro bị u xương mà còn là những bệnh lý khác.",
        "head": "u xương",
        "head_type": "disease",
        "relation": "relatedTo",
        "tail": "bệnh lý",
        "tail_type": "disease"
    },
    {
        "text": "Những hành động và thói quen cần được áp dụng hàng ngày để tăng cường sức khỏe cho bản thân là: Có chế độ dinh dưỡng phù hợp, lành mạnh.",
        "head": "chế độ dinh dưỡng phù hợp, lành mạnh",
        "head_type": "lifestyle",
        "relation": "relatedTo",
        "tail": "sức khỏe",
        "tail_type": "lifestyle"
    },
    {
        "text": "Đặc biệt, cung cấp lượng canxi vừa đủ cho cơ thể",
        "head": "canxi",
        "head_type": "food",
        "relation": "relatedTo",
        "tail": "cơ thể",
        "tail_type": "organ"
    },
    {
        "text": "Thực hiện thăm khám định kỳ 2 lần/năm",
        "head": "thăm khám định kỳ",
        "head_type": "treatment",
        "relation": "relatedTo",
        "tail": "sức khỏe",
        "tail_type": "lifestyle"
    },
    {
        "text": "Tập luyện thể thao để duy trì sức khỏe",
        "head": "tập luyện thể thao",
        "head_type": "lifestyle",
        "relation": "relatedTo",
        "tail": "sức khỏe",
        "tail_type": "lifestyle"
    },
    {
        "text": "Hạn chế tối đa việc tiếp xúc với các chất độc hại, tia phóng xạ",
        "head": "chất độc hại, tia phóng xạ",
        "head_type": "cause",
        "relation": "causedBy",
        "tail": "u xương",
        "tail_type": "disease"
    },
    {
        "text": "Có ý thức ngừa bệnh sớm nếu người trong gia đình có bệnh sử liên quan đến xương hoặc ung thư xương",
        "head": "bệnh sử liên quan đến xương hoặc ung thư xương",
        "head_type": "cause",
        "relation": "causedBy",
        "tail": "u xương",
        "tail_type": "disease"
    },
    {
        "text": "Trung tâm Chấn thương chỉnh hình, Hệ thống BVĐK Tâm Anh, là nơi quy tụ đội ngũ chuyên gia đầu ngành, bác sĩ ngoại khoa giàu kinh nghiệm, tận tâm, nhiệt tình như: TTND.GS.TS.BS Nguyễn Việt Tiến; PGS.TS.BS Đặng Hồng Hoa; TS.BS Tăng Hà Nam Anh; ThS.BS.CKII Trần Anh Vũ; BS.CKI Trần Xuân Anh, ThS.BS.CKI Lê Đình Khoa, ThS.BS Nguyễn Quang Tôn Quyền; TS.BS Đỗ Tiến Dũng; TS.BS.CKII Vũ Hữu Dũng…",
        "head": "Trung tâm Chấn thương chỉnh hình, Hệ thống BVĐK Tâm Anh",
        "head_type": "treatment",
        "relation": "treatedBy",
        "tail": "u xương",
        "tail_type": "disease"
    },
    {
        "text": "Đây cũng là một trong những đơn vị tiên phong trong việc chẩn đoán và điều trị các bệnh về cơ xương khớp với kỹ thuật hiện đại theo phác đồ cập nhật quốc tế.",
        "head": "chẩn đoán và điều trị",
        "head_type": "treatment",
        "relation": "treatedBy",
        "tail": "bệnh về cơ xương khớp",
        "tail_type": "disease"
    },
    {
        "text": "Bệnh viện còn được trang bị hệ thống máy móc, trang thiết bị chẩn đoán hình ảnh hiện đại như: máy chụp CT 768 lát cắt Somatom Drive, máy cộng hưởng từ thế hệ mới Magnetom Amira BioMatrix, robot Artis Pheno, máy đo mật độ xương, máy siêu âm…; hệ thống kính vi phẫu thuật Opmi Vario 700 Zeiss, bàn mổ Meera-Maquet… để có thể phát hiện sớm các tổn thương và điều trị hiệu quả các bệnh lý về cơ xương khớp…",
        "head": "máy chụp CT 768 lát cắt Somatom Drive, máy cộng hưởng từ thế hệ mới Magnetom Amira BioMatrix, robot Artis Pheno, máy đo mật độ xương, máy siêu âm…; hệ thống kính vi phẫu thuật Opmi Vario 700 Zeiss, bàn mổ Meera-Maquet…",
        "head_type": "test",
        "relation": "diagnosedBy",
        "tail": "bệnh lý về cơ xương khớp",
        "tail_type": "disease"
    }
]