[
    {
        "text": "Xuất huyết tử cung bất thường là tình trạng bệnh lý xảy ra có thể liên quan đến u xơ tử cung, polype lòng tử cung, rối loạn nội tiết, tăng sinh nội mạc tử cung, bướu tại cổ tử cung, viêm nhiễm, bệnh lý huyết học…",
        "head": "Xuất huyết tử cung bất thường",
        "head_type": "disease",
        "relation": "causedBy",
        "tail": "u xơ tử cung",
        "tail_type": "disease"
    },
    {
        "text": "Xuất huyết tử cung bất thường là tình trạng bệnh lý xảy ra có thể liên quan đến u xơ tử cung, polype lòng tử cung, rối loạn nội tiết, tăng sinh nội mạc tử cung, bướu tại cổ tử cung, viêm nhiễm, bệnh lý huyết học…",
        "head": "Xuất huyết tử cung bất thường",
        "head_type": "disease",
        "relation": "causedBy",
        "tail": "polype lòng tử cung",
        "tail_type": "disease"
    },
    {
        "text": "Xuất huyết tử cung bất thường là tình trạng bệnh lý xảy ra có thể liên quan đến u xơ tử cung, polype lòng tử cung, rối loạn nội tiết, tăng sinh nội mạc tử cung, bướu tại cổ tử cung, viêm nhiễm, bệnh lý huyết học…",
        "head": "Xuất huyết tử cung bất thường",
        "head_type": "disease",
        "relation": "causedBy",
        "tail": "rối loạn nội tiết",
        "tail_type": "disease"
    },
    {
        "text": "Xuất huyết tử cung bất thường là tình trạng bệnh lý xảy ra có thể liên quan đến u xơ tử cung, polype lòng tử cung, rối loạn nội tiết, tăng sinh nội mạc tử cung, bướu tại cổ tử cung, viêm nhiễm, bệnh lý huyết học…",
        "head": "Xuất huyết tử cung bất thường",
        "head_type": "disease",
        "relation": "causedBy",
        "tail": "tăng sinh nội mạc tử cung",
        "tail_type": "disease"
    },
    {
        "text": "Xuất huyết tử cung bất thường là tình trạng bệnh lý xảy ra có thể liên quan đến u xơ tử cung, polype lòng tử cung, rối loạn nội tiết, tăng sinh nội mạc tử cung, bướu tại cổ tử cung, viêm nhiễm, bệnh lý huyết học…",
        "head": "Xuất huyết tử cung bất thường",
        "head_type": "disease",
        "relation": "causedBy",
        "tail": "bướu tại cổ tử cung",
        "tail_type": "disease"
    },
    {
        "text": "Xuất huyết tử cung bất thường là tình trạng bệnh lý xảy ra có thể liên quan đến u xơ tử cung, polype lòng tử cung, rối loạn nội tiết, tăng sinh nội mạc tử cung, bướu tại cổ tử cung, viêm nhiễm, bệnh lý huyết học…",
        "head": "Xuất huyết tử cung bất thường",
        "head_type": "disease",
        "relation": "causedBy",
        "tail": "viêm nhiễm",
        "tail_type": "disease"
    },
    {
        "text": "Xuất huyết tử cung bất thường là tình trạng bệnh lý xảy ra có thể liên quan đến u xơ tử cung, polype lòng tử cung, rối loạn nội tiết, tăng sinh nội mạc tử cung, bướu tại cổ tử cung, viêm nhiễm, bệnh lý huyết học…",
        "head": "Xuất huyết tử cung bất thường",
        "head_type": "disease",
        "relation": "causedBy",
        "tail": "bệnh lý huyết học",
        "tail_type": "disease"
    },
    {
        "text": "Bệnh gây ra các triệu chứng chảy máu vùng kín, xảy ra tự nhiên có hay không có liên quan đến chu kỳ kinh, hoặc sau quan hệ tình dục.",
        "head": "chảy máu vùng kín",
        "head_type": "symptom",
        "relation": "isSymptomOf",
        "tail": "Xuất huyết tử cung bất thường",
        "tail_type": "disease"
    },
    {
        "text": "Xuất huyết tử cung bất thường (thuật ngữ Y khoa là Abnormal Uterine Bleeding - AUB) là tình trạng chảy máu từ tử cung một cách bất thường, khác với các đặc điểm của một chu kỳ kinh nguyệt bình thường.",
        "head": "Xuất huyết tử cung bất thường",
        "head_type": "disease",
        "relation": "isSymptomOf",
        "tail": "chảy máu từ tử cung một cách bất thường",
        "tail_type": "symptom"
    },
    {
        "text": "Xuất huyết tử cung bất thường (thuật ngữ Y khoa là Abnormal Uterine Bleeding - AUB) là tình trạng chảy máu từ tử cung một cách bất thường, khác với các đặc điểm của một chu kỳ kinh nguyệt bình thường.",
        "head": "Xuất huyết tử cung bất thường",
        "head_type": "disease",
        "relation": "relatedTo",
        "tail": "chu kỳ kinh nguyệt bình thường",
        "tail_type": "lifestyle"
    },
    {
        "text": "Tình trạng này làm ảnh hưởng sức khỏe khoảng 1/3 dân số phụ nữ ở độ tuổi sinh sản.",
        "head": "Xuất huyết tử cung bất thường",
        "head_type": "disease",
        "relation": "affects",
        "tail": "sức khỏe",
        "tail_type": "lifestyle"
    },
    {
        "text": "Việc chẩn đoán nguyên nhân của tình trạng này khá khó khăn và phức tạp.",
        "head": "Xuất huyết tử cung bất thường",
        "head_type": "disease",
        "relation": "diagnosedBy",
        "tail": "chẩn đoán",
        "tail_type": "test"
    },
    {
        "text": "Do đó, ngay khi có các triệu chứng bất thường, các chị em nên đến ngay cơ sở y tế để được điều trị kịp thời.",
        "head": "triệu chứng bất thường",
        "head_type": "symptom",
        "relation": "isSymptomOf",
        "tail": "Xuất huyết tử cung bất thường",
        "tail_type": "disease"
    },
    {
        "text": "Do đó, ngay khi có các triệu chứng bất thường, các chị em nên đến ngay cơ sở y tế để được điều trị kịp thời.",
        "head": "Xuất huyết tử cung bất thường",
        "head_type": "disease",
        "relation": "treatedBy",
        "tail": "điều trị",
        "tail_type": "treatment"
    },
    {
        "text": "Một chu kỳ kinh nguyệt được tính từ ngày đầu tiên ra máu kinh của lần hành kinh này cho đến ngày đầu tiên ra máu kinh của lần hành kinh tiếp theo.",
        "head": "chu kỳ kinh nguyệt",
        "head_type": "lifestyle",
        "relation": "relatedTo",
        "tail": "ra máu kinh",
        "tail_type": "symptom"
    },
    {
        "text": "Thông thường, chu kỳ kinh nguyệt kéo dài trong khoảng 21 - 35 ngày, hành kinh khoảng từ 3 - 8 ngày, những ngày đầu tiên kinh thường ra nhiều, sau đó giảm dần và sạch kinh.",
        "head": "chu kỳ kinh nguyệt",
        "head_type": "lifestyle",
        "relation": "relatedTo",
        "tail": "hành kinh",
        "tail_type": "symptom"
    },
    {
        "text": "Nếu chu kỳ kinh nguyệt ngắn hơn 21 ngày hay kéo dài hơn 35 ngày, hoặc thay đổi không hành kinh từ 3 - 6 tháng (còn gọi là vô kinh) đều phải được xem là bất thường.",
        "head": "chu kỳ kinh nguyệt",
        "head_type": "lifestyle",
        "relation": "relatedTo",
        "tail": "vô kinh",
        "tail_type": "disease"
    },
    {
        "text": "BS.CKII Nguyễn Bá Mỹ Nhi, Giám đốc Trung tâm Sản Phụ khoa, Bệnh viện Đa khoa Tâm Anh TP.HCM cho biết, có rất nhiều nguyên nhân gây ra tình trạng xuất huyết tử cung bất thường, các nguyên nhân này được hệ thống hóa lại nằm trong các chữ cái viết tắt tên các nguyên nhân và nhóm các nguyên nhân (PALM & COEIN) giúp các bác sĩ phụ khoa dễ dàng tìm kiếm nguyên nhân gây bệnh một cách toàn diện để điều trị phù hợp.",
        "head": "Xuất huyết tử cung bất thường",
        "head_type": "disease",
        "relation": "causedBy",
        "tail": "PALM & COEIN",
        "tail_type": "cause"
    },
    {
        "text": "Hệ thống phân loại nguyên nhân theo PALM & COEIN được Liên đoàn Sản Phụ khoa Quốc tế (FIGO) mô tả từ năm 2011, bao gồm: Polype lòng tử cung Bệnh cơ tuyến tử cung hay bệnh lý lạc tuyến nội mạc tử cung vào cơ tử cung U xơ tử cung Các bướu ác tính tử cung Bệnh lý đông cầm máu Rối loạn phóng noãn Lạc nội mạc cổ tử cung Chảy máu do các điều trị khác gây ra Bệnh lý chưa xác định rõ",
        "head": "PALM & COEIN",
        "head_type": "cause",
        "relation": "causedBy",
        "tail": "Polype lòng tử cung",
        "tail_type": "disease"
    },
    {
        "text": "Hệ thống phân loại nguyên nhân theo PALM & COEIN được Liên đoàn Sản Phụ khoa Quốc tế (FIGO) mô tả từ năm 2011, bao gồm: Polype lòng tử cung Bệnh cơ tuyến tử cung hay bệnh lý lạc tuyến nội mạc tử cung vào cơ tử cung U xơ tử cung Các bướu ác tính tử cung Bệnh lý đông cầm máu Rối loạn phóng noãn Lạc nội mạc cổ tử cung Chảy máu do các điều trị khác gây ra Bệnh lý chưa xác định rõ",
        "head": "PALM & COEIN",
        "head_type": "cause",
        "relation": "causedBy",
        "tail": "Bệnh cơ tuyến tử cung",
        "tail_type": "disease"
    },
    {
        "text": "Hệ thống phân loại nguyên nhân theo PALM & COEIN được Liên đoàn Sản Phụ khoa Quốc tế (FIGO) mô tả từ năm 2011, bao gồm: Polype lòng tử cung Bệnh cơ tuyến tử cung hay bệnh lý lạc tuyến nội mạc tử cung vào cơ tử cung U xơ tử cung Các bướu ác tính tử cung Bệnh lý đông cầm máu Rối loạn phóng noãn Lạc nội mạc cổ tử cung Chảy máu do các điều trị khác gây ra Bệnh lý chưa xác định rõ",
        "head": "PALM & COEIN",
        "head_type": "cause",
        "relation": "causedBy",
        "tail": "bệnh lý lạc tuyến nội mạc tử cung vào cơ tử cung",
        "tail_type": "disease"
    },
    {
        "text": "Hệ thống phân loại nguyên nhân theo PALM & COEIN được Liên đoàn Sản Phụ khoa Quốc tế (FIGO) mô tả từ năm 2011, bao gồm: Polype lòng tử cung Bệnh cơ tuyến tử cung hay bệnh lý lạc tuyến nội mạc tử cung vào cơ tử cung U xơ tử cung Các bướu ác tính tử cung Bệnh lý đông cầm máu Rối loạn phóng noãn Lạc nội mạc cổ tử cung Chảy máu do các điều trị khác gây ra Bệnh lý chưa xác định rõ",
        "head": "PALM & COEIN",
        "head_type": "cause",
        "relation": "causedBy",
        "tail": "U xơ tử cung",
        "tail_type": "disease"
    },
    {
        "text": "Hệ thống phân loại nguyên nhân theo PALM & COEIN được Liên đoàn Sản Phụ khoa Quốc tế (FIGO) mô tả từ năm 2011, bao gồm: Polype lòng tử cung Bệnh cơ tuyến tử cung hay bệnh lý lạc tuyến nội mạc tử cung vào cơ tử cung U xơ tử cung Các bướu ác tính tử cung Bệnh lý đông cầm máu Rối loạn phóng noãn Lạc nội mạc cổ tử cung Chảy máu do các điều trị khác gây ra Bệnh lý chưa xác định rõ",
        "head": "PALM & COEIN",
        "head_type": "cause",
        "relation": "causedBy",
        "tail": "Các bướu ác tính tử cung",
        "tail_type": "disease"
    },
    {
        "text": "Hệ thống phân loại nguyên nhân theo PALM & COEIN được Liên đoàn Sản Phụ khoa Quốc tế (FIGO) mô tả từ năm 2011, bao gồm: Polype lòng tử cung Bệnh cơ tuyến tử cung hay bệnh lý lạc tuyến nội mạc tử cung vào cơ tử cung U xơ tử cung Các bướu ác tính tử cung Bệnh lý đông cầm máu Rối loạn phóng noãn Lạc nội mạc cổ tử cung Chảy máu do các điều trị khác gây ra Bệnh lý chưa xác định rõ",
        "head": "PALM & COEIN",
        "head_type": "cause",
        "relation": "causedBy",
        "tail": "Bệnh lý đông cầm máu",
        "tail_type": "disease"
    },
    {
        "text": "Hệ thống phân loại nguyên nhân theo PALM & COEIN được Liên đoàn Sản Phụ khoa Quốc tế (FIGO) mô tả từ năm 2011, bao gồm: Polype lòng tử cung Bệnh cơ tuyến tử cung hay bệnh lý lạc tuyến nội mạc tử cung vào cơ tử cung U xơ tử cung Các bướu ác tính tử cung Bệnh lý đông cầm máu Rối loạn phóng noãn Lạc nội mạc cổ tử cung Chảy máu do các điều trị khác gây ra Bệnh lý chưa xác định rõ",
        "head": "PALM & COEIN",
        "head_type": "cause",
        "relation": "causedBy",
        "tail": "Rối loạn phóng noãn",
        "tail_type": "disease"
    },
    {
        "text": "Hệ thống phân loại nguyên nhân theo PALM & COEIN được Liên đoàn Sản Phụ khoa Quốc tế (FIGO) mô tả từ năm 2011, bao gồm: Polype lòng tử cung Bệnh cơ tuyến tử cung hay bệnh lý lạc tuyến nội mạc tử cung vào cơ tử cung U xơ tử cung Các bướu ác tính tử cung Bệnh lý đông cầm máu Rối loạn phóng noãn Lạc nội mạc cổ tử cung Chảy máu do các điều trị khác gây ra Bệnh lý chưa xác định rõ",
        "head": "PALM & COEIN",
        "head_type": "cause",
        "relation": "causedBy",
        "tail": "Lạc nội mạc cổ tử cung",
        "tail_type": "disease"
    },
    {
        "text": "Hệ thống phân loại nguyên nhân theo PALM & COEIN được Liên đoàn Sản Phụ khoa Quốc tế (FIGO) mô tả từ năm 2011, bao gồm: Polype lòng tử cung Bệnh cơ tuyến tử cung hay bệnh lý lạc tuyến nội mạc tử cung vào cơ tử cung U xơ tử cung Các bướu ác tính tử cung Bệnh lý đông cầm máu Rối loạn phóng noãn Lạc nội mạc cổ tử cung Chảy máu do các điều trị khác gây ra Bệnh lý chưa xác định rõ",
        "head": "PALM & COEIN",
        "head_type": "cause",
        "relation": "causedBy",
        "tail": "Chảy máu do các điều trị khác gây ra",
        "tail_type": "disease"
    },
    {
        "text": "Hệ thống phân loại nguyên nhân theo PALM & COEIN được Liên đoàn Sản Phụ khoa Quốc tế (FIGO) mô tả từ năm 2011, bao gồm: Polype lòng tử cung Bệnh cơ tuyến tử cung hay bệnh lý lạc tuyến nội mạc tử cung vào cơ tử cung U xơ tử cung Các bướu ác tính tử cung Bệnh lý đông cầm máu Rối loạn phóng noãn Lạc nội mạc cổ tử cung Chảy máu do các điều trị khác gây ra Bệnh lý chưa xác định rõ",
        "head": "PALM & COEIN",
        "head_type": "cause",
        "relation": "causedBy",
        "tail": "Bệnh lý chưa xác định rõ",
        "tail_type": "disease"
    },
    {
        "text": "Các chị em phụ nữ có thể nhận biết các dấu hiệu của bệnh lý thông qua các triệu chứng đi kèm ban đầu như rối loạn kinh nguyệt (kinh kéo dài, lượng nhiều, ra kinh không đúng ngày dự kiến, chảy máu sau giao hợp…), rối loạn tiểu tiện, đau tức vùng hạ vị…",
        "head": "rối loạn kinh nguyệt",
        "head_type": "symptom",
        "relation": "isSymptomOf",
        "tail": "Xuất huyết tử cung bất thường",
        "tail_type": "disease"
    },
    {
        "text": "Các chị em phụ nữ có thể nhận biết các dấu hiệu của bệnh lý thông qua các triệu chứng đi kèm ban đầu như rối loạn kinh nguyệt (kinh kéo dài, lượng nhiều, ra kinh không đúng ngày dự kiến, chảy máu sau giao hợp…), rối loạn tiểu tiện, đau tức vùng hạ vị…",
        "head": "kinh kéo dài",
        "head_type": "symptom",
        "relation": "isSymptomOf",
        "tail": "Xuất huyết tử cung bất thường",
        "tail_type": "disease"
    },
    {
        "text": "Các chị em phụ nữ có thể nhận biết các dấu hiệu của bệnh lý thông qua các triệu chứng đi kèm ban đầu như rối loạn kinh nguyệt (kinh kéo dài, lượng nhiều, ra kinh không đúng ngày dự kiến, chảy máu sau giao hợp…), rối loạn tiểu tiện, đau tức vùng hạ vị…",
        "head": "lượng nhiều",
        "head_type": "symptom",
        "relation": "isSymptomOf",
        "tail": "Xuất huyết tử cung bất thường",
        "tail_type": "disease"
    },
    {
        "text": "Các chị em phụ nữ có thể nhận biết các dấu hiệu của bệnh lý thông qua các triệu chứng đi kèm ban đầu như rối loạn kinh nguyệt (kinh kéo dài, lượng nhiều, ra kinh không đúng ngày dự kiến, chảy máu sau giao hợp…), rối loạn tiểu tiện, đau tức vùng hạ vị…",
        "head": "ra kinh không đúng ngày dự kiến",
        "head_type": "symptom",
        "relation": "isSymptomOf",
        "tail": "Xuất huyết tử cung bất thường",
        "tail_type": "disease"
    },
    {
        "text": "Các chị em phụ nữ có thể nhận biết các dấu hiệu của bệnh lý thông qua các triệu chứng đi kèm ban đầu như rối loạn kinh nguyệt (kinh kéo dài, lượng nhiều, ra kinh không đúng ngày dự kiến, chảy máu sau giao hợp…), rối loạn tiểu tiện, đau tức vùng hạ vị…",
        "head": "chảy máu sau giao hợp",
        "head_type": "symptom",
        "relation": "isSymptomOf",
        "tail": "Xuất huyết tử cung bất thường",
        "tail_type": "disease"
    },
    {
        "text": "Các chị em phụ nữ có thể nhận biết các dấu hiệu của bệnh lý thông qua các triệu chứng đi kèm ban đầu như rối loạn kinh nguyệt (kinh kéo dài, lượng nhiều, ra kinh không đúng ngày dự kiến, chảy máu sau giao hợp…), rối loạn tiểu tiện, đau tức vùng hạ vị…",
        "head": "rối loạn tiểu tiện",
        "head_type": "symptom",
        "relation": "isSymptomOf",
        "tail": "Xuất huyết tử cung bất thường",
        "tail_type": "disease"
    },
    {
        "text": "Các chị em phụ nữ có thể nhận biết các dấu hiệu của bệnh lý thông qua các triệu chứng đi kèm ban đầu như rối loạn kinh nguyệt (kinh kéo dài, lượng nhiều, ra kinh không đúng ngày dự kiến, chảy máu sau giao hợp…), rối loạn tiểu tiện, đau tức vùng hạ vị…",
        "head": "đau tức vùng hạ vị",
        "head_type": "symptom",
        "relation": "isSymptomOf",
        "tail": "Xuất huyết tử cung bất thường",
        "tail_type": "disease"
    },
    {
        "text": "Nếu không được điều trị kịp thời và đúng cách, xuất huyết âm đạo bất thường có thể sẽ gây ảnh hưởng đến chức năng mang thai, sinh sản, và ảnh hưởng đáng kể đến chất lượng sống của người phụ nữ.",
        "head": "Xuất huyết âm đạo bất thường",
        "head_type": "disease",
        "relation": "affects",
        "tail": "chức năng mang thai",
        "tail_type": "lifestyle"
    },
    {
        "text": "Nếu không được điều trị kịp thời và đúng cách, xuất huyết âm đạo bất thường có thể sẽ gây ảnh hưởng đến chức năng mang thai, sinh sản, và ảnh hưởng đáng kể đến chất lượng sống của người phụ nữ.",
        "head": "Xuất huyết âm đạo bất thường",
        "head_type": "disease",
        "relation": "affects",
        "tail": "sinh sản",
        "tail_type": "lifestyle"
    },
    {
        "text": "Nếu không được điều trị kịp thời và đúng cách, xuất huyết âm đạo bất thường có thể sẽ gây ảnh hưởng đến chức năng mang thai, sinh sản, và ảnh hưởng đáng kể đến chất lượng sống của người phụ nữ.",
        "head": "Xuất huyết âm đạo bất thường",
        "head_type": "disease",
        "relation": "affects",
        "tail": "chất lượng sống",
        "tail_type": "lifestyle"
    },
    {
        "text": "Đau tức vùng hạ vị, rối loạn kinh nguyệt… là những triệu chứng thường gặp của các bệnh lý sản phụ khoa gây xuất huyết tử cung bất thường",
        "head": "đau tức vùng hạ vị",
        "head_type": "symptom",
        "relation": "isSymptomOf",
        "tail": "Xuất huyết tử cung bất thường",
        "tail_type": "disease"
    },
    {
        "text": "Các thời điểm và một số hình thái xuất huyết tử cung bất thường (3)  Xuất huyết giữa chu kỳ kinh, hoặc không liên quan đến chu kỳ kinh.",
        "head": "Xuất huyết giữa chu kỳ kinh",
        "head_type": "symptom",
        "relation": "isSymptomOf",
        "tail": "Xuất huyết tử cung bất thường",
        "tail_type": "disease"
    },
    {
        "text": "Các thời điểm và một số hình thái xuất huyết tử cung bất thường (3)  Xuất huyết giữa chu kỳ kinh, hoặc không liên quan đến chu kỳ kinh.",
        "head": "Xuất huyết không liên quan đến chu kỳ kinh",
        "head_type": "symptom",
        "relation": "isSymptomOf",
        "tail": "Xuất huyết tử cung bất thường",
        "tail_type": "disease"
    },
    {
        "text": "Xuất huyết ở tuổi dậy thì hoặc quanh mãn kinh, sau mãn kinh.",
        "head": "Xuất huyết ở tuổi dậy thì",
        "head_type": "symptom",
        "relation": "isSymptomOf",
        "tail": "Xuất huyết tử cung bất thường",
        "tail_type": "disease"
    },
    {
        "text": "Xuất huyết ở tuổi dậy thì hoặc quanh mãn kinh, sau mãn kinh.",
        "head": "Xuất huyết quanh mãn kinh",
        "head_type": "symptom",
        "relation": "isSymptomOf",
        "tail": "Xuất huyết tử cung bất thường",
        "tail_type": "disease"
    },
    {
        "text": "Xuất huyết ở tuổi dậy thì hoặc quanh mãn kinh, sau mãn kinh.",
        "head": "Xuất huyết sau mãn kinh",
        "head_type": "symptom",
        "relation": "isSymptomOf",
        "tail": "Xuất huyết tử cung bất thường",
        "tail_type": "disease"
    },
    {
        "text": "Xuất huyết sau quan hệ tình dục.",
        "head": "Xuất huyết sau quan hệ tình dục",
        "head_type": "symptom",
        "relation": "isSymptomOf",
        "tail": "Xuất huyết tử cung bất thường",
        "tail_type": "disease"
    },
    {
        "text": "Ra máu kiểu nhỏ giọt lượng ít vào bất kỳ thời điểm nào trong kỳ kinh nguyệt.",
        "head": "Ra máu kiểu nhỏ giọt lượng ít",
        "head_type": "symptom",
        "relation": "isSymptomOf",
        "tail": "Xuất huyết tử cung bất thường",
        "tail_type": "disease"
    },
    {
        "text": "Ra máu lượng nhiều (cường kinh), ra máu kéo dài hơn 8 ngày so với bình thường (rong kinh).",
        "head": "Ra máu lượng nhiều",
        "head_type": "symptom",
        "relation": "isSymptomOf",
        "tail": "Xuất huyết tử cung bất thường",
        "tail_type": "disease"
    },
    {
        "text": "Ra máu lượng nhiều (cường kinh), ra máu kéo dài hơn 8 ngày so với bình thường (rong kinh).",
        "head": "Ra máu kéo dài hơn 8 ngày",
        "head_type": "symptom",
        "relation": "isSymptomOf",
        "tail": "Xuất huyết tử cung bất thường",
        "tail_type": "disease"
    },
    {
        "text": "Xuất huyết sau 6 - 12 tuần sau sinh, sau mổ lấy thai, sau nạo hút thai…",
        "head": "Xuất huyết sau sinh",
        "head_type": "symptom",
        "relation": "isSymptomOf",
        "tail": "Xuất huyết tử cung bất thường",
        "tail_type": "disease"
    },
    {
        "text": "Xuất huyết sau 6 - 12 tuần sau sinh, sau mổ lấy thai, sau nạo hút thai…",
        "head": "Xuất huyết sau mổ lấy thai",
        "head_type": "symptom",
        "relation": "isSymptomOf",
        "tail": "Xuất huyết tử cung bất thường",
        "tail_type": "disease"
    },
    {
        "text": "Xuất huyết sau 6 - 12 tuần sau sinh, sau mổ lấy thai, sau nạo hút thai…",
        "head": "Xuất huyết sau nạo hút thai",
        "head_type": "symptom",
        "relation": "isSymptomOf",
        "tail": "Xuất huyết tử cung bất thường",
        "tail_type": "disease"
    },
    {
        "text": "Xuất huyết sau sử dụng một số thuốc, thường là thuốc nội tiết.",
        "head": "Xuất huyết sau sử dụng thuốc nội tiết",
        "head_type": "symptom",
        "relation": "isSymptomOf",
        "tail": "Xuất huyết tử cung bất thường",
        "tail_type": "disease"
    },
    {
        "text": "Đầu tiên, bác sĩ sẽ thăm hỏi về sức khỏe của bạn và gia đình, cũng như khai thác sâu các vấn đề về chu kỳ kinh nguyệt của bạn.",
        "head": "Thăm hỏi sức khỏe",
        "head_type": "treatment",
        "relation": "treatedBy",
        "tail": "Xuất huyết tử cung bất thường",
        "tail_type": "disease"
    },
    {
        "text": "Do đó, bạn nên ghi lại chi tiết về chu kỳ kinh trước khi gặp bác sĩ như ngày bắt đầu có kinh, thời gian kéo dài mỗi chu kỳ, lượng kinh như thế nào (ít, bình thường, nhiều hay nhỏ giọt…), có kèm triệu chứng đau bụng nhiều hay không…",
        "head": "Ghi lại chi tiết chu kỳ kinh",
        "head_type": "lifestyle",
        "relation": "relatedTo",
        "tail": "Xuất huyết tử cung bất thường",
        "tail_type": "disease"
    },
    {
        "text": "BS.CKII Nguyễn Bá Mỹ Nhi đang thực hiện ca mổ tại Trung tâm Sản Phụ khoa BVĐK Tâm Anh TP.HCM Tiếp đến, bác sĩ tiến hành kiểm tra phụ khoa tổng quát,",
        "head": "Kiểm tra phụ khoa tổng quát",
        "head_type": "test",
        "relation": "diagnosedBy",
        "tail": "Xuất huyết tử cung bất thường",
        "tail_type": "disease"
    },
    {
        "text": "và có thể chỉ định thêm một số xét nghiệm và cận lâm sàng cần thiết:",
        "head": "Xét nghiệm và cận lâm sàng",
        "head_type": "test",
        "relation": "diagnosedBy",
        "tail": "Xuất huyết tử cung bất thường",
        "tail_type": "disease"
    },
    {
        "text": "Xét nghiệm máu đánh giá loại trừ có thai, đánh giá có thiếu máu không và mức độ thiếu máu; có rối loạn nội tiết không; có rối loạn đông máu, rối loạn chức năng gan thận không…",
        "head": "Xét nghiệm máu",
        "head_type": "test",
        "relation": "diagnosedBy",
        "tail": "Xuất huyết tử cung bất thường",
        "tail_type": "disease"
    },
    {
        "text": "Siêu âm vùng chậu, siêu âm bơm dịch vào buồng tử cung.",
        "head": "Siêu âm vùng chậu",
        "head_type": "test",
        "relation": "diagnosedBy",
        "tail": "Xuất huyết tử cung bất thường",
        "tail_type": "disease"
    },
    {
        "text": "Siêu âm vùng chậu, siêu âm bơm dịch vào buồng tử cung.",
        "head": "Siêu âm bơm dịch vào buồng tử cung",
        "head_type": "test",
        "relation": "diagnosedBy",
        "tail": "Xuất huyết tử cung bất thường",
        "tail_type": "disease"
    },
    {
        "text": "Chụp MRI hoặc CT scan vùng bụng chậu.",
        "head": "Chụp MRI",
        "head_type": "test",
        "relation": "diagnosedBy",
        "tail": "Xuất huyết tử cung bất thường",
        "tail_type": "disease"
    },
    {
        "text": "Chụp MRI hoặc CT scan vùng bụng chậu.",
        "head": "CT scan vùng bụng chậu",
        "head_type": "test",
        "relation": "diagnosedBy",
        "tail": "Xuất huyết tử cung bất thường",
        "tail_type": "disease"
    },
    {
        "text": "Nội soi buồng tử cung.",
        "head": "Nội soi buồng tử cung",
        "head_type": "test",
        "relation": "diagnosedBy",
        "tail": "Xuất huyết tử cung bất thường",
        "tail_type": "disease"
    },
    {
        "text": "Hút sinh thiết nội mạc tử cung.",
        "head": "Hút sinh thiết nội mạc tử cung",
        "head_type": "test",
        "relation": "diagnosedBy",
        "tail": "Xuất huyết tử cung bất thường",
        "tail_type": "disease"
    },
    {
        "text": "Tình trạng xuất huyết tử cung bất thường không chỉ ảnh hưởng đến sức khỏe, mà còn tác động tiêu cực đến tâm lý của bệnh nhân.",
        "head": "Xuất huyết tử cung bất thường",
        "head_type": "disease",
        "relation": "affects",
        "tail": "Sức khỏe",
        "tail_type": "organ"
    },
    {
        "text": "Tình trạng xuất huyết tử cung bất thường không chỉ ảnh hưởng đến sức khỏe, mà còn tác động tiêu cực đến tâm lý của bệnh nhân.",
        "head": "Xuất huyết tử cung bất thường",
        "head_type": "disease",
        "relation": "affects",
        "tail": "Tâm lý",
        "tail_type": "organ"
    },
    {
        "text": "Nếu không được can thiệp điều trị kịp thời, chị em phụ nữ có nguy cơ phải đối mặt với nhiều biến chứng nguy hiểm như: Thiếu máu mãn và nặng dẫn đến suy tim, suy nhược cơ thể, mất khả năng tập trung làm việc, vô sinh, sảy thai, sảy thai tiếp, sinh non, thai chết trong tử cung… hoặc bỏ sót các bệnh lý ác tính diễn tiến qua giai đoạn xa và nặng.",
        "head": "Thiếu máu mãn và nặng",
        "head_type": "disease",
        "relation": "causedBy",
        "tail": "Xuất huyết tử cung bất thường",
        "tail_type": "disease"
    },
    {
        "text": "Nếu không được can thiệp điều trị kịp thời, chị em phụ nữ có nguy cơ phải đối mặt với nhiều biến chứng nguy hiểm như: Thiếu máu mãn và nặng dẫn đến suy tim, suy nhược cơ thể, mất khả năng tập trung làm việc, vô sinh, sảy thai, sảy thai tiếp, sinh non, thai chết trong tử cung… hoặc bỏ sót các bệnh lý ác tính diễn tiến qua giai đoạn xa và nặng.",
        "head": "Suy tim",
        "head_type": "disease",
        "relation": "causedBy",
        "tail": "Xuất huyết tử cung bất thường",
        "tail_type": "disease"
    },
    {
        "text": "Nếu không được can thiệp điều trị kịp thời, chị em phụ nữ có nguy cơ phải đối mặt với nhiều biến chứng nguy hiểm như: Thiếu máu mãn và nặng dẫn đến suy tim, suy nhược cơ thể, mất khả năng tập trung làm việc, vô sinh, sảy thai, sảy thai tiếp, sinh non, thai chết trong tử cung… hoặc bỏ sót các bệnh lý ác tính diễn tiến qua giai đoạn xa và nặng.",
        "head": "Suy nhược cơ thể",
        "head_type": "disease",
        "relation": "causedBy",
        "tail": "Xuất huyết tử cung bất thường",
        "tail_type": "disease"
    },
    {
        "text": "Nếu không được can thiệp điều trị kịp thời, chị em phụ nữ có nguy cơ phải đối mặt với nhiều biến chứng nguy hiểm như: Thiếu máu mãn và nặng dẫn đến suy tim, suy nhược cơ thể, mất khả năng tập trung làm việc, vô sinh, sảy thai, sảy thai tiếp, sinh non, thai chết trong tử cung… hoặc bỏ sót các bệnh lý ác tính diễn tiến qua giai đoạn xa và nặng.",
        "head": "Mất khả năng tập trung làm việc",
        "head_type": "symptom",
        "relation": "causedBy",
        "tail": "Xuất huyết tử cung bất thường",
        "tail_type": "disease"
    },
    {
        "text": "Nếu không được can thiệp điều trị kịp thời, chị em phụ nữ có nguy cơ phải đối mặt với nhiều biến chứng nguy hiểm như: Thiếu máu mãn và nặng dẫn đến suy tim, suy nhược cơ thể, mất khả năng tập trung làm việc, vô sinh, sảy thai, sảy thai tiếp, sinh non, thai chết trong tử cung… hoặc bỏ sót các bệnh lý ác tính diễn tiến qua giai đoạn xa và nặng.",
        "head": "Vô sinh",
        "head_type": "disease",
        "relation": "causedBy",
        "tail": "Xuất huyết tử cung bất thường",
        "tail_type": "disease"
    },
    {
        "text": "Nếu không được can thiệp điều trị kịp thời, chị em phụ nữ có nguy cơ phải đối mặt với nhiều biến chứng nguy hiểm như: Thiếu máu mãn và nặng dẫn đến suy tim, suy nhược cơ thể, mất khả năng tập trung làm việc, vô sinh, sảy thai, sảy thai tiếp, sinh non, thai chết trong tử cung… hoặc bỏ sót các bệnh lý ác tính diễn tiến qua giai đoạn xa và nặng.",
        "head": "Sảy thai",
        "head_type": "disease",
        "relation": "causedBy",
        "tail": "Xuất huyết tử cung bất thường",
        "tail_type": "disease"
    },
    {
        "text": "Nếu không được can thiệp điều trị kịp thời, chị em phụ nữ có nguy cơ phải đối mặt với nhiều biến chứng nguy hiểm như: Thiếu máu mãn và nặng dẫn đến suy tim, suy nhược cơ thể, mất khả năng tập trung làm việc, vô sinh, sảy thai, sảy thai tiếp, sinh non, thai chết trong tử cung… hoặc bỏ sót các bệnh lý ác tính diễn tiến qua giai đoạn xa và nặng.",
        "head": "Sảy thai tiếp",
        "head_type": "disease",
        "relation": "causedBy",
        "tail": "Xuất huyết tử cung bất thường",
        "tail_type": "disease"
    },
    {
        "text": "Nếu không được can thiệp điều trị kịp thời, chị em phụ nữ có nguy cơ phải đối mặt với nhiều biến chứng nguy hiểm như: Thiếu máu mãn và nặng dẫn đến suy tim, suy nhược cơ thể, mất khả năng tập trung làm việc, vô sinh, sảy thai, sảy thai tiếp, sinh non, thai chết trong tử cung… hoặc bỏ sót các bệnh lý ác tính diễn tiến qua giai đoạn xa và nặng.",
        "head": "Sinh non",
        "head_type": "disease",
        "relation": "causedBy",
        "tail": "Xuất huyết tử cung bất thường",
        "tail_type": "disease"
    },
    {
        "text": "Nếu không được can thiệp điều trị kịp thời, chị em phụ nữ có nguy cơ phải đối mặt với nhiều biến chứng nguy hiểm như: Thiếu máu mãn và nặng dẫn đến suy tim, suy nhược cơ thể, mất khả năng tập trung làm việc, vô sinh, sảy thai, sảy thai tiếp, sinh non, thai chết trong tử cung… hoặc bỏ sót các bệnh lý ác tính diễn tiến qua giai đoạn xa và nặng.",
        "head": "Thai chết trong tử cung",
        "head_type": "disease",
        "relation": "causedBy",
        "tail": "Xuất huyết tử cung bất thường",
        "tail_type": "disease"
    },
    {
        "text": "BS.CKII Nguyễn Bá Mỹ Nhi cho biết, việc xác định phương pháp điều trị sẽ phụ thuộc vào nguyên nhân gây xuất huyết tử cung bất thường và một số yếu tố khác như độ tuổi, số con đã có và mong muốn sinh con của bệnh nhân.",
        "head": "xuất huyết tử cung bất thường",
        "head_type": "symptom",
        "relation": "causedBy",
        "tail": "nguyên nhân",
        "tail_type": "cause"
    },
    {
        "text": "BS.CKII Nguyễn Bá Mỹ Nhi cho biết, việc xác định phương pháp điều trị sẽ phụ thuộc vào nguyên nhân gây xuất huyết tử cung bất thường và một số yếu tố khác như độ tuổi, số con đã có và mong muốn sinh con của bệnh nhân.",
        "head": "xuất huyết tử cung bất thường",
        "head_type": "symptom",
        "relation": "relatedTo",
        "tail": "độ tuổi",
        "tail_type": "lifestyle"
    },
    {
        "text": "BS.CKII Nguyễn Bá Mỹ Nhi cho biết, việc xác định phương pháp điều trị sẽ phụ thuộc vào nguyên nhân gây xuất huyết tử cung bất thường và một số yếu tố khác như độ tuổi, số con đã có và mong muốn sinh con của bệnh nhân.",
        "head": "xuất huyết tử cung bất thường",
        "head_type": "symptom",
        "relation": "relatedTo",
        "tail": "số con đã có",
        "tail_type": "lifestyle"
    },
    {
        "text": "BS.CKII Nguyễn Bá Mỹ Nhi cho biết, việc xác định phương pháp điều trị sẽ phụ thuộc vào nguyên nhân gây xuất huyết tử cung bất thường và một số yếu tố khác như độ tuổi, số con đã có và mong muốn sinh con của bệnh nhân.",
        "head": "xuất huyết tử cung bất thường",
        "head_type": "symptom",
        "relation": "relatedTo",
        "tail": "mong muốn sinh con",
        "tail_type": "lifestyle"
    },
    {
        "text": "Tùy nguyên nhân mà các điều trị có thể là nội khoa (điều trị bằng thuốc) hoặc là ngoại khoa (can thiệp phẫu thuật).",
        "head": "xuất huyết tử cung bất thường",
        "head_type": "symptom",
        "relation": "treatedBy",
        "tail": "nội khoa",
        "tail_type": "treatment"
    },
    {
        "text": "Tùy nguyên nhân mà các điều trị có thể là nội khoa (điều trị bằng thuốc) hoặc là ngoại khoa (can thiệp phẫu thuật).",
        "head": "xuất huyết tử cung bất thường",
        "head_type": "symptom",
        "relation": "treatedBy",
        "tail": "ngoại khoa",
        "tail_type": "treatment"
    },
    {
        "text": "Tùy nguyên nhân mà các điều trị có thể là nội khoa (điều trị bằng thuốc) hoặc là ngoại khoa (can thiệp phẫu thuật).",
        "head": "nội khoa",
        "head_type": "treatment",
        "relation": "relatedTo",
        "tail": "điều trị bằng thuốc",
        "tail_type": "treatment"
    },
    {
        "text": "Tùy nguyên nhân mà các điều trị có thể là nội khoa (điều trị bằng thuốc) hoặc là ngoại khoa (can thiệp phẫu thuật).",
        "head": "ngoại khoa",
        "head_type": "treatment",
        "relation": "relatedTo",
        "tail": "can thiệp phẫu thuật",
        "tail_type": "treatment"
    },
    {
        "text": "Tùy vào nguyên nhân gây xuất huyết tử cung bất thường mà bác sĩ sẽ có chỉ định điều trị phù hợp và hiệu quả",
        "head": "xuất huyết tử cung bất thường",
        "head_type": "symptom",
        "relation": "treatedBy",
        "tail": "điều trị phù hợp",
        "tail_type": "treatment"
    }
]